<OAI-PMH xmlns:xsi="http://www.w3.org/2001/XMLSchema-instance" xsi:schemaLocation="http://www.openarchives.org/OAI/2.0/ http://www.openarchives.org/OAI/2.0/OAI-PMH.xsd" xmlns="http://www.openarchives.org/OAI/2.0/">
  <responseDate>2018-09-21T10:16:04Z</responseDate>
  <request verb="ListRecords" resumptionToken="%7C%7C%7Coai_dc%7C113%7C2018-09-21T10%3A16%3A03Z">http://www.spc.int/DigitalLibrary/OAI</request>
  <ListRecords>
    <record>
      <header>
        <identifier>oai:www.spc.int:0f376048-a199-40c4-856b-fe3587565ecb</identifier>
        <datestamp>2018-01-31T03:20:14Z</datestamp>
        <setSpec>All_FishNews</setSpec>
        <setSpec>FishNews_154</setSpec>
        <setSpec>All_InfoBull</setSpec>
      </header>
      <metadata>
        <oai_dc:dc xmlns:oai_dc="http://www.openarchives.org/OAI/2.0/oai_dc/" xmlns:dc="http://purl.org/dc/elements/1.1/" xmlns:xsi="http://www.w3.org/2001/XMLSchema-instance" xsi:schemaLocation="http://www.openarchives.org/OAI/2.0/oai_dc/ http://www.openarchives.org/OAI/2.0/oai_dc.xsd">
          <dc:title>Local fish names added to PacFishID</dc:title>
          <dc:creator>Anon.</dc:creator>
          <dc:description>Anon. 2018. Local fish names added to PacFishID. SPC Fisheries Newsletter 154:16.</dc:description>
          <dc:date>2018</dc:date>
          <dc:type>Text</dc:type>
          <dc:format>application/pdf</dc:format>
          <dc:identifier>http://www.spc.int/DigitalLibrary/Doc/FAME/InfoBull/FishNews/154/FishNews154_18_Anon.pdf</dc:identifier>
          <dc:language>en</dc:language>
        </oai_dc:dc>
      </metadata>
    </record>
    <record>
      <header>
        <identifier>oai:www.spc.int:adda9569-da1b-44f8-9f2e-fe37af7ec9df</identifier>
        <datestamp>2012-07-30T21:28:24Z</datestamp>
        <setSpec>RTMF_25</setSpec>
        <setSpec>All_Meetings</setSpec>
      </header>
      <metadata>
        <oai_dc:dc xmlns:oai_dc="http://www.openarchives.org/OAI/2.0/oai_dc/" xmlns:dc="http://purl.org/dc/elements/1.1/" xmlns:xsi="http://www.w3.org/2001/XMLSchema-instance" xsi:schemaLocation="http://www.openarchives.org/OAI/2.0/oai_dc/ http://www.openarchives.org/OAI/2.0/oai_dc.xsd">
          <dc:title>SPC Coastal Fisheries Programme Training section activities August 1992-March 1994</dc:title>
          <dc:creator>Anon.</dc:creator>
          <dc:subject>Fisheries</dc:subject>
          <dc:subject>Training needs</dc:subject>
          <dc:description>Anon. 1994. SPC Coastal Fisheries Programme Training section activities August 1992-March 1994 [Information Paper 10]. Noumea, New Caledonia: South Pacific Commission. Regional Technical Meeting on Fisheries, Noumea, New Caledonia, 14-18 March 1994, 25th. 10 p.</dc:description>
          <dc:publisher>South Pacific Commission</dc:publisher>
          <dc:date>1994</dc:date>
          <dc:type>Text</dc:type>
          <dc:format>application/pdf</dc:format>
          <dc:identifier>http://www.spc.int/DigitalLibrary/Doc/FAME/Meetings/RTMF/25/IP10.pdf</dc:identifier>
          <dc:language>en</dc:language>
        </oai_dc:dc>
      </metadata>
    </record>
    <record>
      <header>
        <identifier>oai:www.spc.int:9268fd0b-7d63-4ba5-84b7-fe3f510f3d16</identifier>
        <datestamp>2015-08-31T04:47:03Z</datestamp>
        <setSpec>All_InfoBull</setSpec>
        <setSpec>All_TRAD</setSpec>
        <setSpec>TRAD_24</setSpec>
      </header>
      <metadata>
        <oai_dc:dc xmlns:oai_dc="http://www.openarchives.org/OAI/2.0/oai_dc/" xmlns:dc="http://purl.org/dc/elements/1.1/" xmlns:xsi="http://www.w3.org/2001/XMLSchema-instance" xsi:schemaLocation="http://www.openarchives.org/OAI/2.0/oai_dc/ http://www.openarchives.org/OAI/2.0/oai_dc.xsd">
          <dc:title>The role of social capital in a common property resource system in coastal areas: A case study of community-based coastal resource management in Fiji</dc:title>
          <dc:creator>Sano Y.</dc:creator>
          <dc:subject>Fishery management</dc:subject>
          <dc:description>Sano Y. 2008. The role of social capital in a common property resource system in coastal areas: A case study of community-based coastal resource management in Fiji. SPC Traditional Marine Resource Management and Knowledge Information Bulletin 24:19-32.</dc:description>
          <dc:date>2008</dc:date>
          <dc:type>Text</dc:type>
          <dc:format>application/pdf</dc:format>
          <dc:identifier>http://www.spc.int/DigitalLibrary/Doc/FAME/InfoBull/TRAD/24/Trad24_19_Sano.pdf</dc:identifier>
          <dc:language>en</dc:language>
          <dc:coverage>Fiji</dc:coverage>
        </oai_dc:dc>
      </metadata>
    </record>
    <record>
      <header>
        <identifier>oai:www.spc.int:61ffdc05-aabc-4f43-9dd0-fe4ab23d759d</identifier>
        <datestamp>2015-06-16T21:31:40Z</datestamp>
        <setSpec>posters_MarineSpecies</setSpec>
        <setSpec>Posters</setSpec>
      </header>
      <metadata>
        <oai_dc:dc xmlns:oai_dc="http://www.openarchives.org/OAI/2.0/oai_dc/" xmlns:dc="http://purl.org/dc/elements/1.1/" xmlns:xsi="http://www.w3.org/2001/XMLSchema-instance" xsi:schemaLocation="http://www.openarchives.org/OAI/2.0/oai_dc/ http://www.openarchives.org/OAI/2.0/oai_dc.xsd">
          <dc:title>Most common pelagic fish species of Nauru</dc:title>
          <dc:creator>Anon.</dc:creator>
          <dc:description>Anon. 2004. Most common pelagic fish species of Nauru [Poster]. Noumea, New Caledonia: SPC, Secretariat of the Pacific Community.</dc:description>
          <dc:date>2004</dc:date>
          <dc:type>Text</dc:type>
          <dc:format>application/pdf</dc:format>
          <dc:identifier>http://www.spc.int/DigitalLibrary/Doc/FAME/Posters/Nauru_offshore.pdf</dc:identifier>
          <dc:language>en</dc:language>
          <dc:coverage>Nauru</dc:coverage>
        </oai_dc:dc>
      </metadata>
    </record>
    <record>
      <header>
        <identifier>oai:www.spc.int:85a4a4ad-7edd-48f0-a147-fe5528cb1f78</identifier>
        <datestamp>2015-08-27T03:35:23Z</datestamp>
        <setSpec>All_FishNews</setSpec>
        <setSpec>All_InfoBull</setSpec>
      </header>
      <metadata>
        <oai_dc:dc xmlns:oai_dc="http://www.openarchives.org/OAI/2.0/oai_dc/" xmlns:dc="http://purl.org/dc/elements/1.1/" xmlns:xsi="http://www.w3.org/2001/XMLSchema-instance" xsi:schemaLocation="http://www.openarchives.org/OAI/2.0/oai_dc/ http://www.openarchives.org/OAI/2.0/oai_dc.xsd">
          <dc:title>La norme ISO 22000 : système de management de la sécurité alimentaire</dc:title>
          <dc:creator>Talbot V.</dc:creator>
          <dc:description>Talbot V. 2007. La norme ISO 22000 : système de management de la sécurité alimentaire. Lettre d'information sur les pêches de la CPS 120:40-43.</dc:description>
          <dc:date>2007</dc:date>
          <dc:type>Text</dc:type>
          <dc:format>application/pdf</dc:format>
          <dc:identifier>http://www.spc.int/DigitalLibrary/Doc/FAME/InfoBull/FishNews_VF/120/FishNews120VF_40_Talbot.pdf</dc:identifier>
          <dc:language>fr</dc:language>
        </oai_dc:dc>
      </metadata>
    </record>
    <record>
      <header>
        <identifier>oai:www.spc.int:578ef1ab-f153-4ac9-8bb8-fe57ba897c45</identifier>
        <datestamp>2014-07-24T23:29:55Z</datestamp>
        <setSpec>All_Reports</setSpec>
        <setSpec>CRISP</setSpec>
      </header>
      <metadata>
        <oai_dc:dc xmlns:oai_dc="http://www.openarchives.org/OAI/2.0/oai_dc/" xmlns:dc="http://purl.org/dc/elements/1.1/" xmlns:xsi="http://www.w3.org/2001/XMLSchema-instance" xsi:schemaLocation="http://www.openarchives.org/OAI/2.0/oai_dc/ http://www.openarchives.org/OAI/2.0/oai_dc.xsd">
          <dc:title>Inventaire des coraux scléractiniaires du grand lagon nord de la Nouvelle-Calédonie</dc:title>
          <dc:creator>Lasne G.</dc:creator>
          <dc:description>Lasne G. 2010. Inventaire des coraux scléractiniaires du grand lagon nord de la Nouvelle-Calédonie. Noumea, New Caledonia: Coral Reef Initiatives for the Pacific (CRISP). 124 p.</dc:description>
          <dc:date>2010</dc:date>
          <dc:type>Text</dc:type>
          <dc:format>application/pdf</dc:format>
          <dc:identifier>http://www.spc.int/DigitalLibrary/Doc/FAME/Reports/CRISP/FR_2010_Inventaire_coraux_scleractiniaires.pdf</dc:identifier>
          <dc:language>fr</dc:language>
        </oai_dc:dc>
      </metadata>
    </record>
    <record>
      <header>
        <identifier>oai:www.spc.int:1a93c800-3053-4fc7-a4fe-fe6324cfba2b</identifier>
        <datestamp>2012-07-30T21:28:24Z</datestamp>
        <setSpec>All_Meetings</setSpec>
        <setSpec>SCTB_3</setSpec>
      </header>
      <metadata>
        <oai_dc:dc xmlns:oai_dc="http://www.openarchives.org/OAI/2.0/oai_dc/" xmlns:dc="http://purl.org/dc/elements/1.1/" xmlns:xsi="http://www.w3.org/2001/XMLSchema-instance" xsi:schemaLocation="http://www.openarchives.org/OAI/2.0/oai_dc/ http://www.openarchives.org/OAI/2.0/oai_dc.xsd">
          <dc:title>Bibliography Tuna and Billfish assessment programme publications, 1989-90</dc:title>
          <dc:creator>Anon.</dc:creator>
          <dc:subject>Billfish fisheries</dc:subject>
          <dc:subject>Tuna fisheries</dc:subject>
          <dc:description>Anon. 1990. Bibliography Tuna and Billfish assessment programme publications, 1989-90 [WP14]. Noumea, New Caledonia: South Pacific Commission. Standing Committee on Tuna and Billfish, Noumea, New Caledonia, 6-8 June 1990, 3rd. 2 p.</dc:description>
          <dc:publisher>South Pacific Commission</dc:publisher>
          <dc:date>1990</dc:date>
          <dc:type>Text</dc:type>
          <dc:format>application/pdf</dc:format>
          <dc:identifier>http://www.spc.int/DigitalLibrary/Doc/FAME/Meetings/SCTB/3/WP14.pdf</dc:identifier>
          <dc:language>en</dc:language>
        </oai_dc:dc>
      </metadata>
    </record>
    <record>
      <header>
        <identifier>oai:www.spc.int:e2eb5d4d-1b48-4526-afdd-fe6e4a051802</identifier>
        <datestamp>2017-03-21T00:53:51Z</datestamp>
        <setSpec>All_InfoBull</setSpec>
        <setSpec>All_BDM</setSpec>
        <setSpec>BDM_37</setSpec>
      </header>
      <metadata>
        <oai_dc:dc xmlns:oai_dc="http://www.openarchives.org/OAI/2.0/oai_dc/" xmlns:dc="http://purl.org/dc/elements/1.1/" xmlns:xsi="http://www.w3.org/2001/XMLSchema-instance" xsi:schemaLocation="http://www.openarchives.org/OAI/2.0/oai_dc/ http://www.openarchives.org/OAI/2.0/oai_dc.xsd">
          <dc:title>An aquarium trade dendrochirotid holothurian, &lt;em&gt;Pseudocolochirus&lt;/em&gt; sp., processed into &lt;em&gt;teripang&lt;/em&gt; in Sulawesi, Indonesia</dc:title>
          <dc:creator>Yusuf S.</dc:creator>
          <dc:creator>Tuwo A.</dc:creator>
          <dc:creator>Tresnati J.</dc:creator>
          <dc:creator>Conand C.</dc:creator>
          <dc:subject>Aquarium fish collecting</dc:subject>
          <dc:subject>Sea cucumbers</dc:subject>
          <dc:description>Yusuf S., Tuwo A., Tresnati J., Conand C. 2017. An aquarium trade dendrochirotid holothurian, &lt;em&gt;Pseudocolochirus&lt;/em&gt; sp., processed into &lt;em&gt;teripang&lt;/em&gt; in Sulawesi, Indonesia. SPC Beche-de-mer Information Bulletin 37:116.</dc:description>
          <dc:date>2017</dc:date>
          <dc:type>Text</dc:type>
          <dc:format>application/pdf</dc:format>
          <dc:identifier>http://www.spc.int/DigitalLibrary/Doc/FAME/InfoBull/BDM/37/BDM37_116_Yusuf.pdf</dc:identifier>
          <dc:language>en</dc:language>
          <dc:coverage>Indonesia</dc:coverage>
        </oai_dc:dc>
      </metadata>
    </record>
    <record>
      <header>
        <identifier>oai:www.spc.int:c0a2626c-586c-4d43-8306-fe6f5b6ea686</identifier>
        <datestamp>2012-07-30T21:28:24Z</datestamp>
        <setSpec>All_Meetings</setSpec>
        <setSpec>WCPFC_SC1</setSpec>
      </header>
      <metadata>
        <oai_dc:dc xmlns:oai_dc="http://www.openarchives.org/OAI/2.0/oai_dc/" xmlns:dc="http://purl.org/dc/elements/1.1/" xmlns:xsi="http://www.w3.org/2001/XMLSchema-instance" xsi:schemaLocation="http://www.openarchives.org/OAI/2.0/oai_dc/ http://www.openarchives.org/OAI/2.0/oai_dc.xsd">
          <dc:title>Diet of large pelagic predators of the Western and Central Pacific Ocean</dc:title>
          <dc:creator>Allain V.</dc:creator>
          <dc:subject>Tuna fisheries</dc:subject>
          <dc:description>Allain,V. 2005. Diet of large pelagic predators of the Western and Central Pacific Ocean [BI WP-2]. Kolonia, Pohnpei State, Federated States of Micronesia: Western and Central Pacific Fisheries Commission. Meeting of the Scientific Committee of the Western and Central Pacific Fisheries Commission, Noumea, New Caledonia, 8-19 August 2005, 1st. 16 p.</dc:description>
          <dc:date>2005</dc:date>
          <dc:type>Text</dc:type>
          <dc:format>application/pdf</dc:format>
          <dc:identifier>http://www.spc.int/DigitalLibrary/Doc/FAME/Meetings/WCPFC/SC1/SC1_BI_WP_2.pdf</dc:identifier>
          <dc:language>en</dc:language>
        </oai_dc:dc>
      </metadata>
    </record>
    <record>
      <header>
        <identifier>oai:www.spc.int:08a06527-4abb-4588-bd3e-fe77a7da9acf</identifier>
        <datestamp>2015-08-20T22:09:28Z</datestamp>
        <setSpec>All_InfoBull</setSpec>
        <setSpec>All _LRF</setSpec>
        <setSpec>LRF_8</setSpec>
      </header>
      <metadata>
        <oai_dc:dc xmlns:oai_dc="http://www.openarchives.org/OAI/2.0/oai_dc/" xmlns:dc="http://purl.org/dc/elements/1.1/" xmlns:xsi="http://www.w3.org/2001/XMLSchema-instance" xsi:schemaLocation="http://www.openarchives.org/OAI/2.0/oai_dc/ http://www.openarchives.org/OAI/2.0/oai_dc.xsd">
          <dc:title>Seed supply for grouper cage culture in Khanh Hoa, Vietnam</dc:title>
          <dc:creator>Tuan L.A.</dc:creator>
          <dc:creator>Hambrey J.</dc:creator>
          <dc:description>Tuan L.A., Hambrey J. 2001. Seed supply for grouper cage culture in Khanh Hoa, Vietnam. SPC Live Reef Fish Information Bulletin 8:33-36.</dc:description>
          <dc:date>2001</dc:date>
          <dc:type>Text</dc:type>
          <dc:format>application/pdf</dc:format>
          <dc:identifier>http://www.spc.int/DigitalLibrary/Doc/FAME/InfoBull/LRF/8/LRF8_33_Tuan.pdf</dc:identifier>
          <dc:language>en</dc:language>
          <dc:coverage>Vietnam</dc:coverage>
        </oai_dc:dc>
      </metadata>
    </record>
    <record>
      <header>
        <identifier>oai:www.spc.int:576ee4c0-c47b-4cb0-a9d5-fe7dd0232495</identifier>
        <datestamp>2015-08-19T22:00:52Z</datestamp>
        <setSpec>FAD_3</setSpec>
        <setSpec>All_InfoBull</setSpec>
      </header>
      <metadata>
        <oai_dc:dc xmlns:oai_dc="http://www.openarchives.org/OAI/2.0/oai_dc/" xmlns:dc="http://purl.org/dc/elements/1.1/" xmlns:xsi="http://www.w3.org/2001/XMLSchema-instance" xsi:schemaLocation="http://www.openarchives.org/OAI/2.0/oai_dc/ http://www.openarchives.org/OAI/2.0/oai_dc.xsd">
          <dc:title>The dynamics and effects of FADs in La Reunion Island</dc:title>
          <dc:creator>Detolle J.P.</dc:creator>
          <dc:creator>Tessier E.</dc:creator>
          <dc:creator>Roos D.</dc:creator>
          <dc:creator>Rene F.</dc:creator>
          <dc:creator>Sacchi J.</dc:creator>
          <dc:subject>Fish aggregation devices</dc:subject>
          <dc:description>Detolle J.P., Tessier E., Roos D., Rene F., Sacchi J. 1998. The dynamics and effects of FADs in La Reunion Island. SPC Fish Aggregating Device Information Bulletin 3:19-23.</dc:description>
          <dc:date>1998</dc:date>
          <dc:type>Text</dc:type>
          <dc:format>application/pdf</dc:format>
          <dc:identifier>http://www.spc.int/DigitalLibrary/Doc/FAME/InfoBull/FAD/3/FAD3_19_Detolle.pdf</dc:identifier>
          <dc:language>en</dc:language>
          <dc:coverage>Reunion Island</dc:coverage>
        </oai_dc:dc>
      </metadata>
    </record>
    <record>
      <header>
        <identifier>oai:www.spc.int:2236b6f2-8140-48d2-b4b8-fe81c9a9db84</identifier>
        <datestamp>2012-07-30T21:28:24Z</datestamp>
        <setSpec>NC_ALL</setSpec>
        <setSpec>All_InfoBull</setSpec>
        <setSpec>SPB</setSpec>
      </header>
      <metadata>
        <oai_dc:dc xmlns:oai_dc="http://www.openarchives.org/OAI/2.0/oai_dc/" xmlns:dc="http://purl.org/dc/elements/1.1/" xmlns:xsi="http://www.w3.org/2001/XMLSchema-instance" xsi:schemaLocation="http://www.openarchives.org/OAI/2.0/oai_dc/ http://www.openarchives.org/OAI/2.0/oai_dc.xsd">
          <dc:title>Fisheries training course opens in Noumea</dc:title>
          <dc:creator>Anon.</dc:creator>
          <dc:subject>Fisheries</dc:subject>
          <dc:description>Anon. 1957. Fisheries training course opens in Noumea. Noumea, New Caledonia: South Pacific Commission. SPC Quarterly Bulletin Vol. 7, No. 1, January 1957, p. 10-12</dc:description>
          <dc:publisher>South Pacific Commission</dc:publisher>
          <dc:date>1957</dc:date>
          <dc:type>Text</dc:type>
          <dc:format>application/pdf</dc:format>
          <dc:identifier>http://www.spc.int/DigitalLibrary/Doc/FAME/InfoBull/SPB/SPB7_1_SPC.pdf</dc:identifier>
          <dc:language>en</dc:language>
          <dc:coverage>New Caledonia</dc:coverage>
        </oai_dc:dc>
      </metadata>
    </record>
    <record>
      <header>
        <identifier>oai:www.spc.int:36864950-fd10-47f1-a91b-fe858cf84c95</identifier>
        <datestamp>2015-08-19T04:58:53Z</datestamp>
        <setSpec>BDM_VF_21</setSpec>
        <setSpec>All_BDM</setSpec>
        <setSpec>All_InfoBull</setSpec>
      </header>
      <metadata>
        <oai_dc:dc xmlns:oai_dc="http://www.openarchives.org/OAI/2.0/oai_dc/" xmlns:dc="http://purl.org/dc/elements/1.1/" xmlns:xsi="http://www.w3.org/2001/XMLSchema-instance" xsi:schemaLocation="http://www.openarchives.org/OAI/2.0/oai_dc/ http://www.openarchives.org/OAI/2.0/oai_dc.xsd">
          <dc:title>Observations de pontes de &lt;i&gt;Bohadschia vitiensis&lt;/i&gt; et &lt;i&gt;Holothuria scabra versicolor&lt;/i&gt; en milieu naturel</dc:title>
          <dc:creator>Desurmont A.</dc:creator>
          <dc:subject>Sea cucumbers</dc:subject>
          <dc:description>Desurmont A. 2005. Observations de pontes de &lt;i&gt;Bohadschia vitiensis&lt;/i&gt; et &lt;i&gt;Holothuria scabra versicolor&lt;/i&gt; en milieu naturel. La Bêche-de-mer, Bulletin d'information de la CPS 21:28.</dc:description>
          <dc:date>2005</dc:date>
          <dc:type>Text</dc:type>
          <dc:format>application/pdf</dc:format>
          <dc:identifier>http://www.spc.int/DigitalLibrary/Doc/FAME/InfoBull/BDM_VF/21/BDM21VF_28_Desurmont.pdf</dc:identifier>
          <dc:language>fr</dc:language>
        </oai_dc:dc>
      </metadata>
    </record>
    <record>
      <header>
        <identifier>oai:www.spc.int:28fc41f6-72ae-459a-aaa4-fe86e90c0558</identifier>
        <datestamp>2012-07-30T21:28:24Z</datestamp>
        <setSpec>RTMF_22</setSpec>
        <setSpec>All_Meetings</setSpec>
      </header>
      <metadata>
        <oai_dc:dc xmlns:oai_dc="http://www.openarchives.org/OAI/2.0/oai_dc/" xmlns:dc="http://purl.org/dc/elements/1.1/" xmlns:xsi="http://www.w3.org/2001/XMLSchema-instance" xsi:schemaLocation="http://www.openarchives.org/OAI/2.0/oai_dc/ http://www.openarchives.org/OAI/2.0/oai_dc.xsd">
          <dc:title>Fish aggregating devices: are they really of any help to fishing? Example: South West Efate (Vanuatu)</dc:title>
          <dc:creator>Cillaurren E.</dc:creator>
          <dc:subject>Fishing</dc:subject>
          <dc:subject>Fisheries</dc:subject>
          <dc:subject>Fishing</dc:subject>
          <dc:subject>Fish aggregation devices</dc:subject>
          <dc:description>Cillaurren E. 1990. Fish aggregating devices: are they really of any help to fishing? Example: South West Efate (Vanuatu) [WP 28]. Noumea, New Caledonia: South Pacific Commission. Regional Technical Meeting on Fisheries, Noumea, New Caledonia, 6-10 August 1990, 22nd. 9 p.</dc:description>
          <dc:publisher>South Pacific Commission</dc:publisher>
          <dc:date>1990</dc:date>
          <dc:type>Text</dc:type>
          <dc:format>application/pdf</dc:format>
          <dc:identifier>http://www.spc.int/DigitalLibrary/Doc/FAME/Meetings/RTMF/22/WP28.pdf</dc:identifier>
          <dc:language>en</dc:language>
          <dc:coverage>Vanuatu</dc:coverage>
        </oai_dc:dc>
      </metadata>
    </record>
    <record>
      <header>
        <identifier>oai:www.spc.int:1964b1d3-2123-446c-8014-fe8e0b6dc4e2</identifier>
        <datestamp>2012-07-30T21:28:24Z</datestamp>
        <setSpec>SPB</setSpec>
        <setSpec>All_InfoBull</setSpec>
      </header>
      <metadata>
        <oai_dc:dc xmlns:oai_dc="http://www.openarchives.org/OAI/2.0/oai_dc/" xmlns:dc="http://purl.org/dc/elements/1.1/" xmlns:xsi="http://www.w3.org/2001/XMLSchema-instance" xsi:schemaLocation="http://www.openarchives.org/OAI/2.0/oai_dc/ http://www.openarchives.org/OAI/2.0/oai_dc.xsd">
          <dc:title>Fisheries in Netherlands New Guinea make steady progress</dc:title>
          <dc:creator>Pel H.V.</dc:creator>
          <dc:subject>Fisheries</dc:subject>
          <dc:description>Pel H.V. 1959. Fisheries in Netherlands New Guinea make steady progress. Noumea, New Caledonia: South Pacific Commission. SPC Quarterly Bulletin Vol. 9, No. 4, October 1959, p. 31</dc:description>
          <dc:publisher>South Pacific Commission</dc:publisher>
          <dc:date>1959</dc:date>
          <dc:type>Text</dc:type>
          <dc:format>application/pdf</dc:format>
          <dc:identifier>http://www.spc.int/DigitalLibrary/Doc/FAME/InfoBull/SPB/SPB9_4_Pel.pdf</dc:identifier>
          <dc:language>en</dc:language>
          <dc:coverage>Papua New Guinea</dc:coverage>
        </oai_dc:dc>
      </metadata>
    </record>
    <record>
      <header>
        <identifier>oai:www.spc.int:977ffa04-62c0-45db-9fc1-fe946197ec91</identifier>
        <datestamp>2012-07-30T21:28:24Z</datestamp>
        <setSpec>All_Meetings</setSpec>
        <setSpec>RTMF_10</setSpec>
      </header>
      <metadata>
        <oai_dc:dc xmlns:oai_dc="http://www.openarchives.org/OAI/2.0/oai_dc/" xmlns:dc="http://purl.org/dc/elements/1.1/" xmlns:xsi="http://www.w3.org/2001/XMLSchema-instance" xsi:schemaLocation="http://www.openarchives.org/OAI/2.0/oai_dc/ http://www.openarchives.org/OAI/2.0/oai_dc.xsd">
          <dc:title>Considerations of a workshop on the law of the sea in the Southwest Pacific</dc:title>
          <dc:creator>Anon.</dc:creator>
          <dc:subject>Fisheries</dc:subject>
          <dc:description>Anon. 1978. Considerations of a workshop on the law of the sea in the Southwest Pacific. Manila, Philippines: International Center for Living Aquatic Resources Management (ICLARM). Regional Technical Meeting on Fisheries, Noumea, New Caledonia, 13 - 17 March 1978, 10th. 2 p.</dc:description>
          <dc:publisher>International Center for Living Aquatic Resources Management (ICLARM)</dc:publisher>
          <dc:date>1978</dc:date>
          <dc:type>Text</dc:type>
          <dc:format>application/pdf</dc:format>
          <dc:identifier>http://www.spc.int/DigitalLibrary/Doc/FAME/Meetings/RTMF/10/Considerations_of_a_workshop.pdf</dc:identifier>
          <dc:language>en</dc:language>
        </oai_dc:dc>
      </metadata>
    </record>
    <record>
      <header>
        <identifier>oai:www.spc.int:69cb8da7-b3d3-4448-8728-fe9b687b8e49</identifier>
        <datestamp>2015-08-17T21:58:03Z</datestamp>
        <setSpec>BDM_26</setSpec>
        <setSpec>All_BDM</setSpec>
        <setSpec>All_InfoBull</setSpec>
      </header>
      <metadata>
        <oai_dc:dc xmlns:oai_dc="http://www.openarchives.org/OAI/2.0/oai_dc/" xmlns:dc="http://purl.org/dc/elements/1.1/" xmlns:xsi="http://www.w3.org/2001/XMLSchema-instance" xsi:schemaLocation="http://www.openarchives.org/OAI/2.0/oai_dc/ http://www.openarchives.org/OAI/2.0/oai_dc.xsd">
          <dc:title>Sea cucumbers and other echinoderms at Geyser Bank, Mayotte  (Indian Ocean)</dc:title>
          <dc:creator>Mulochau T.</dc:creator>
          <dc:creator>Conand C.</dc:creator>
          <dc:creator>Quod J.P.</dc:creator>
          <dc:subject>Sea cucumbers</dc:subject>
          <dc:description>Mulochau T., Conand C., Quod J.P. 2007. Sea cucumbers and other echinoderms at Geyser Bank, Mayotte (Indian Ocean). SPC Beche-de-Mer Information Bulletin 26:7-13.</dc:description>
          <dc:date>2007</dc:date>
          <dc:type>Text</dc:type>
          <dc:format>application/pdf</dc:format>
          <dc:identifier>http://www.spc.int/DigitalLibrary/Doc/FAME/InfoBull/BDM/26/BDM26_07_Mulochau.pdf</dc:identifier>
          <dc:language>en</dc:language>
          <dc:coverage>Mayotte Islands</dc:coverage>
        </oai_dc:dc>
      </metadata>
    </record>
    <record>
      <header>
        <identifier>oai:www.spc.int:1954bce9-f7a4-4f3e-9266-fe9ceedd1375</identifier>
        <datestamp>2015-03-30T06:01:55Z</datestamp>
        <setSpec>WCPFC_SC9</setSpec>
        <setSpec>All_Meetings</setSpec>
      </header>
      <metadata>
        <oai_dc:dc xmlns:oai_dc="http://www.openarchives.org/OAI/2.0/oai_dc/" xmlns:dc="http://purl.org/dc/elements/1.1/" xmlns:xsi="http://www.w3.org/2001/XMLSchema-instance" xsi:schemaLocation="http://www.openarchives.org/OAI/2.0/oai_dc/ http://www.openarchives.org/OAI/2.0/oai_dc.xsd">
          <dc:title>Electronic monitoring of seabird bycatch</dc:title>
          <dc:creator>Papworth W.</dc:creator>
          <dc:subject>Electronic monitoring in fisheries</dc:subject>
          <dc:subject>Sea birds--Mortality--Prevention</dc:subject>
          <dc:subject>Fisheries</dc:subject>
          <dc:subject>Sea birds</dc:subject>
          <dc:subject>Tuna fisheries</dc:subject>
          <dc:subject>Bycatches (Fisheries)</dc:subject>
          <dc:description>Papworth W. 2013. Electronic monitoring of seabird bycatch [EB WP 09]. [Pohnpei, Federated States of Micronesia]: Western and Central Pacific Fisheries Commission (WCPFC). Scientific Committee Regular Session, Pohnpei, Federated States of Micronesia, 6-14 August 2013, 9th. 4 p.</dc:description>
          <dc:date>2013</dc:date>
          <dc:type>Text</dc:type>
          <dc:format>application/pdf</dc:format>
          <dc:identifier>http://www.spc.int/DigitalLibrary/Doc/FAME/Meetings/WCPFC/SC9/EB-WP-09-ACAP-Electronic-Monitoring.pdf</dc:identifier>
        </oai_dc:dc>
      </metadata>
    </record>
    <record>
      <header>
        <identifier>oai:www.spc.int:81954cff-afb5-453a-acd4-fe9e41fe66d9</identifier>
        <datestamp>2014-06-18T04:45:36Z</datestamp>
        <setSpec>gestion</setSpec>
        <setSpec>Manuals</setSpec>
        <setSpec>management</setSpec>
        <setSpec>All_Manuals</setSpec>
      </header>
      <metadata>
        <oai_dc:dc xmlns:oai_dc="http://www.openarchives.org/OAI/2.0/oai_dc/" xmlns:dc="http://purl.org/dc/elements/1.1/" xmlns:xsi="http://www.w3.org/2001/XMLSchema-instance" xsi:schemaLocation="http://www.openarchives.org/OAI/2.0/oai_dc/ http://www.openarchives.org/OAI/2.0/oai_dc.xsd">
          <dc:title>La gestion communautaire ds ressources marines - Manuel pour une gestion de la pêche de subsistance par les communautés océaniennes.</dc:title>
          <dc:creator>King M.G.</dc:creator>
          <dc:creator>Lambeth L.</dc:creator>
          <dc:subject>Fisheries</dc:subject>
          <dc:subject>Fishery management</dc:subject>
          <dc:description>King M.G., Lambeth L. 2000. La gestion communautaire ds ressources marines - Manuel pour une gestion de la pêche de subsistance par les communautés océaniennes. Nouméa, Nouvelle-Calédonie: Secrétariat général de la Communauté du Pacifique. 87 p.</dc:description>
          <dc:date>2000</dc:date>
          <dc:type>Text</dc:type>
          <dc:format>application/pdf</dc:format>
          <dc:identifier>http://www.spc.int/DigitalLibrary/Doc/FAME/Manuals/King_00_Community_VF.pdf</dc:identifier>
          <dc:language>fr</dc:language>
        </oai_dc:dc>
      </metadata>
    </record>
    <record>
      <header>
        <identifier>oai:www.spc.int:d7199c21-ca8a-4c1e-a5ad-fe9f3e710198</identifier>
        <datestamp>2015-08-24T03:13:22Z</datestamp>
        <setSpec>All_InfoBull</setSpec>
        <setSpec>FishNews</setSpec>
        <setSpec>All_FishNews</setSpec>
      </header>
      <metadata>
        <oai_dc:dc xmlns:oai_dc="http://www.openarchives.org/OAI/2.0/oai_dc/" xmlns:dc="http://purl.org/dc/elements/1.1/" xmlns:xsi="http://www.w3.org/2001/XMLSchema-instance" xsi:schemaLocation="http://www.openarchives.org/OAI/2.0/oai_dc/ http://www.openarchives.org/OAI/2.0/oai_dc.xsd">
          <dc:title>The South Pacific Islands Fisheries Newsletter #5 - May 1972</dc:title>
          <dc:creator>Anon.</dc:creator>
          <dc:subject>Fisheries</dc:subject>
          <dc:description>Anon. 1972. The South Pacific Islands Fisheries Newsletter 5. Noumea, New Caledonia: The South Pacific Commission. 35 p.</dc:description>
          <dc:date>1972</dc:date>
          <dc:type>Text</dc:type>
          <dc:format>application/pdf</dc:format>
          <dc:identifier>http://www.spc.int/DigitalLibrary/Doc/FAME/InfoBull/FishNews/5/FishNews5.pdf</dc:identifier>
          <dc:language>en</dc:language>
        </oai_dc:dc>
      </metadata>
    </record>
    <record>
      <header>
        <identifier>oai:www.spc.int:dba9c325-322b-42e4-b119-fe9f79807e5f</identifier>
        <datestamp>2015-08-31T00:11:59Z</datestamp>
        <setSpec>POIB_VF_6</setSpec>
        <setSpec>All_POIB</setSpec>
        <setSpec>All_InfoBull</setSpec>
      </header>
      <metadata>
        <oai_dc:dc xmlns:oai_dc="http://www.openarchives.org/OAI/2.0/oai_dc/" xmlns:dc="http://purl.org/dc/elements/1.1/" xmlns:xsi="http://www.w3.org/2001/XMLSchema-instance" xsi:schemaLocation="http://www.openarchives.org/OAI/2.0/oai_dc/ http://www.openarchives.org/OAI/2.0/oai_dc.xsd">
          <dc:title>Une thèse sur la gestion de l'industrie nacrière des Tuamotu</dc:title>
          <dc:creator>Rapaport M.</dc:creator>
          <dc:subject>Pearl oysters</dc:subject>
          <dc:subject>Pearl oyster culture</dc:subject>
          <dc:description>Rapaport M. 1993. Une thèse sur la gestion de l'industrie nacrière des Tuamotu. L'Huître perlière, Bulletin d'information de la CPS 6:10.</dc:description>
          <dc:date>1993</dc:date>
          <dc:type>Text</dc:type>
          <dc:format>application/pdf</dc:format>
          <dc:identifier>http://www.spc.int/DigitalLibrary/Doc/FAME/InfoBull/POIB_VF/6/POIB6VF_10_Rapaport.pdf</dc:identifier>
          <dc:language>fr</dc:language>
          <dc:coverage>French Polynesia</dc:coverage>
        </oai_dc:dc>
      </metadata>
    </record>
    <record>
      <header>
        <identifier>oai:www.spc.int:f25bfc01-efe8-4909-acb1-fea318f327f4</identifier>
        <datestamp>2017-06-22T03:40:27Z</datestamp>
        <setSpec>All_InfoBull</setSpec>
        <setSpec>FishNews_152</setSpec>
        <setSpec>All_FishNews</setSpec>
      </header>
      <metadata>
        <oai_dc:dc xmlns:oai_dc="http://www.openarchives.org/OAI/2.0/oai_dc/" xmlns:dc="http://purl.org/dc/elements/1.1/" xmlns:xsi="http://www.w3.org/2001/XMLSchema-instance" xsi:schemaLocation="http://www.openarchives.org/OAI/2.0/oai_dc/ http://www.openarchives.org/OAI/2.0/oai_dc.xsd">
          <dc:title>Outcomes of the 10th SPC Heads of Fisheries Meeting</dc:title>
          <dc:creator>Anon.</dc:creator>
          <dc:subject>Fisheries</dc:subject>
          <dc:description>Anon. 2017. Outcomes of the 10th SPC Heads of Fisheries Meeting. SPC Fisheries Newsletter 152:16–18.</dc:description>
          <dc:date>2017</dc:date>
          <dc:type>Text</dc:type>
          <dc:format>application/pdf</dc:format>
          <dc:identifier>http://www.spc.int/DigitalLibrary/Doc/FAME/InfoBull/FishNews/152/FishNews152_16_Anon.pdf</dc:identifier>
          <dc:language>en</dc:language>
        </oai_dc:dc>
      </metadata>
    </record>
    <record>
      <header>
        <identifier>oai:www.spc.int:b3d97c66-79b8-4e7f-93c3-fea70cee62b3</identifier>
        <datestamp>2017-12-04T05:37:43Z</datestamp>
        <setSpec>RTMCF_01</setSpec>
      </header>
      <metadata>
        <oai_dc:dc xmlns:oai_dc="http://www.openarchives.org/OAI/2.0/oai_dc/" xmlns:dc="http://purl.org/dc/elements/1.1/" xmlns:xsi="http://www.w3.org/2001/XMLSchema-instance" xsi:schemaLocation="http://www.openarchives.org/OAI/2.0/oai_dc/ http://www.openarchives.org/OAI/2.0/oai_dc.xsd">
          <dc:title>First SPC Regional Technical Meeting on Coastal Fisheries: Agreed Action Plan</dc:title>
          <dc:creator>Anon.</dc:creator>
          <dc:subject>Fisheries</dc:subject>
          <dc:description>Anon. 2017. First SPC Regional Technical Meeting on Coastal Fisheries: Agreed Action Plan.  First SPC Regional Technical Meeting on Coastal Fisheries: 28 November to 1 December 2017, Noumea, New Caledonia. 6 p.</dc:description>
          <dc:date>2017</dc:date>
          <dc:type>Text</dc:type>
          <dc:format>application/pdf</dc:format>
          <dc:identifier>http://www.spc.int/DigitalLibrary/Doc/FAME/Meetings/RTMCF/1/RTMCF_1_Action_Plan.pdf</dc:identifier>
          <dc:language>en</dc:language>
        </oai_dc:dc>
      </metadata>
    </record>
    <record>
      <header>
        <identifier>oai:www.spc.int:175a1e41-6ed8-4351-89ac-fea9c8a6449a</identifier>
        <datestamp>2015-08-28T02:53:47Z</datestamp>
        <setSpec>All _LRF</setSpec>
        <setSpec>LRF_VF_12</setSpec>
        <setSpec>All_InfoBull</setSpec>
      </header>
      <metadata>
        <oai_dc:dc xmlns:oai_dc="http://www.openarchives.org/OAI/2.0/oai_dc/" xmlns:dc="http://purl.org/dc/elements/1.1/" xmlns:xsi="http://www.w3.org/2001/XMLSchema-instance" xsi:schemaLocation="http://www.openarchives.org/OAI/2.0/oai_dc/ http://www.openarchives.org/OAI/2.0/oai_dc.xsd">
          <dc:title>La gestion des concentrations de frai : dernières nouvelles de la &lt;i&gt;Society for the Conservation of Reef Fish Aggregations&lt;/i&gt;</dc:title>
          <dc:creator>Sadovy Y.</dc:creator>
          <dc:description>Sadovy Y. 2004. La gestion des concentrations de frai : dernières nouvelles de la &lt;i&gt;Society for the Conservation of Reef Fish Aggregations&lt;/i&gt;. Ressources marines et commercialisation, Bulletin d'information de la CPS 12:29-30.</dc:description>
          <dc:date>2004</dc:date>
          <dc:type>Text</dc:type>
          <dc:format>application/pdf</dc:format>
          <dc:identifier>http://www.spc.int/DigitalLibrary/Doc/FAME/InfoBull/LRF_VF/12/LRF12VF_29_Sadovy.pdf</dc:identifier>
          <dc:language>fr</dc:language>
        </oai_dc:dc>
      </metadata>
    </record>
    <record>
      <header>
        <identifier>oai:www.spc.int:b3cf1e96-1aa8-4ef2-b41b-feaef8fe723b</identifier>
        <datestamp>2012-07-30T21:28:24Z</datestamp>
        <setSpec>All_Reports</setSpec>
      </header>
      <metadata>
        <oai_dc:dc xmlns:oai_dc="http://www.openarchives.org/OAI/2.0/oai_dc/" xmlns:dc="http://purl.org/dc/elements/1.1/" xmlns:xsi="http://www.w3.org/2001/XMLSchema-instance" xsi:schemaLocation="http://www.openarchives.org/OAI/2.0/oai_dc/ http://www.openarchives.org/OAI/2.0/oai_dc.xsd">
          <dc:title>Eradication of Mozambique tilapia (&lt;i&gt;Oreochromis mossambicus&lt;/i&gt;), restocking of Nile tilapia (&lt;i&gt;O. niloticus&lt;/i&gt;) and improved aquaculture pond management in Nauru</dc:title>
          <dc:creator>Deiye M.</dc:creator>
          <dc:creator>Burramen S.</dc:creator>
          <dc:creator>Burramen L.</dc:creator>
          <dc:creator>Nandlal S.</dc:creator>
          <dc:subject>Aquaculture</dc:subject>
          <dc:subject>Tilapia</dc:subject>
          <dc:description>Deiye M., Burramen S., Burramen L., Nandlal S. 2010. Eradication of Mozambique tilapia (&lt;i&gt;Oreochromis mossambicus&lt;/i&gt;), restocking of Nile tilapia (&lt;i&gt;O. niloticus&lt;/i&gt;) and improved aquaculture pond management in Nauru. [S.l.]: [s.n.]. 8 p.</dc:description>
          <dc:date>2010</dc:date>
          <dc:type>Text</dc:type>
          <dc:format>application/pdf</dc:format>
          <dc:identifier>http://www.spc.int/DigitalLibrary/Doc/FAME/Reports/ACIAR/ACIAR0603_Tilapia_Nauru.pdf</dc:identifier>
          <dc:language>en</dc:language>
          <dc:coverage>Nauru</dc:coverage>
        </oai_dc:dc>
      </metadata>
    </record>
    <record>
      <header>
        <identifier>oai:www.spc.int:3b16023d-0f4b-4ae2-aa0c-feb710a507de</identifier>
        <datestamp>2012-07-30T21:28:24Z</datestamp>
        <setSpec>All_Meetings</setSpec>
        <setSpec>RTMF_18</setSpec>
      </header>
      <metadata>
        <oai_dc:dc xmlns:oai_dc="http://www.openarchives.org/OAI/2.0/oai_dc/" xmlns:dc="http://purl.org/dc/elements/1.1/" xmlns:xsi="http://www.w3.org/2001/XMLSchema-instance" xsi:schemaLocation="http://www.openarchives.org/OAI/2.0/oai_dc/ http://www.openarchives.org/OAI/2.0/oai_dc.xsd">
          <dc:title>Country statement - Fiji</dc:title>
          <dc:creator>Anon.</dc:creator>
          <dc:subject>Fisheries</dc:subject>
          <dc:description>Anon. 1986. Country statement - Fiji [WP 22]. Noumea, New Caledonia: South Pacific Commission. Regional Technical Meeting on Fisheries, Noumea, New Caledonia, 4-8 August 1986, 18th. 8 p.</dc:description>
          <dc:publisher>South Pacific Commission</dc:publisher>
          <dc:date>1986</dc:date>
          <dc:type>Text</dc:type>
          <dc:format>application/pdf</dc:format>
          <dc:identifier>http://www.spc.int/DigitalLibrary/Doc/FAME/Meetings/RTMF/18/WP22.pdf</dc:identifier>
          <dc:language>en</dc:language>
          <dc:coverage>Fiji</dc:coverage>
        </oai_dc:dc>
      </metadata>
    </record>
    <record>
      <header>
        <identifier>oai:www.spc.int:e7cac976-be8d-453c-95cd-feba9ac0e2fd</identifier>
        <datestamp>2018-06-26T22:15:46Z</datestamp>
        <setSpec>Brochures</setSpec>
        <setSpec>Policy_Briefs</setSpec>
      </header>
      <metadata>
        <oai_dc:dc xmlns:oai_dc="http://www.openarchives.org/OAI/2.0/oai_dc/" xmlns:dc="http://purl.org/dc/elements/1.1/" xmlns:xsi="http://www.w3.org/2001/XMLSchema-instance" xsi:schemaLocation="http://www.openarchives.org/OAI/2.0/oai_dc/ http://www.openarchives.org/OAI/2.0/oai_dc.xsd">
          <dc:title>SPC Policy Brief #5: Fisheries and climate change</dc:title>
          <dc:creator>Anon.</dc:creator>
          <dc:subject>Climatic changes</dc:subject>
          <dc:subject>Fisheries</dc:subject>
          <dc:description>Anon. 2008. Fisheries and climate change. Policy Brief, 5/2008. Noumea, New Caledonia: Secretariat of the Pacific Community. [4] p.</dc:description>
          <dc:date>2008</dc:date>
          <dc:type>Text</dc:type>
          <dc:format>application/pdf</dc:format>
          <dc:identifier>http://www.spc.int/DigitalLibrary/Doc/FAME/Brochures/Policy_Brief5_08.pdf</dc:identifier>
          <dc:language>en</dc:language>
        </oai_dc:dc>
      </metadata>
    </record>
    <record>
      <header>
        <identifier>oai:www.spc.int:16bb1c26-c72b-450a-bf69-fec23cba71e1</identifier>
        <datestamp>2012-07-30T21:28:24Z</datestamp>
        <setSpec>RTMF_14</setSpec>
        <setSpec>All_Meetings</setSpec>
      </header>
      <metadata>
        <oai_dc:dc xmlns:oai_dc="http://www.openarchives.org/OAI/2.0/oai_dc/" xmlns:dc="http://purl.org/dc/elements/1.1/" xmlns:xsi="http://www.w3.org/2001/XMLSchema-instance" xsi:schemaLocation="http://www.openarchives.org/OAI/2.0/oai_dc/ http://www.openarchives.org/OAI/2.0/oai_dc.xsd">
          <dc:title>L'océanographie et la biologie des pêches à l'ORSTOM dans l'océan pacifique tropical</dc:title>
          <dc:creator>Anon.</dc:creator>
          <dc:subject>Fisheries</dc:subject>
          <dc:subject>Oceanography</dc:subject>
          <dc:description>Anon. 1982. L'océanographie et la biologie des pêches à l'ORSTOM dans l'océan pacifique tropical [WP 14]. Nouméa, Nouvelle-Calédonie: Commission du Pacifique Sud. Conférence Technique Régionale des Pêches, Nouméa, Nouvelle-Calédonie, 2 - 6 août 1982, 14ème. 7 p.</dc:description>
          <dc:publisher>Commission du Pacifique Sud</dc:publisher>
          <dc:date>1982</dc:date>
          <dc:type>Text</dc:type>
          <dc:format>application/pdf</dc:format>
          <dc:identifier>http://www.spc.int/DigitalLibrary/Doc/FAME/Meetings/RTMF/14/WP14_VF.pdf</dc:identifier>
          <dc:language>fr</dc:language>
        </oai_dc:dc>
      </metadata>
    </record>
    <record>
      <header>
        <identifier>oai:www.spc.int:77b72937-9339-4f83-8310-fec6c759588d</identifier>
        <datestamp>2012-07-30T21:28:24Z</datestamp>
        <setSpec>NC_ALL</setSpec>
        <setSpec>All_Reports</setSpec>
      </header>
      <metadata>
        <oai_dc:dc xmlns:oai_dc="http://www.openarchives.org/OAI/2.0/oai_dc/" xmlns:dc="http://purl.org/dc/elements/1.1/" xmlns:xsi="http://www.w3.org/2001/XMLSchema-instance" xsi:schemaLocation="http://www.openarchives.org/OAI/2.0/oai_dc/ http://www.openarchives.org/OAI/2.0/oai_dc.xsd">
          <dc:title>Rapport concernant l'assistance technique offerte à l'entreprise calédonienne de pêche thonière à la palangre Navimon: 19 août - 23 décembre 1996</dc:title>
          <dc:creator>Beverly S.</dc:creator>
          <dc:creator>Chapman L.B.</dc:creator>
          <dc:subject>Longlines (Fishery equipment)</dc:subject>
          <dc:subject>Longlining (Fisheries)</dc:subject>
          <dc:subject>Tuna fisheries</dc:subject>
          <dc:description>Beverly S., Chapman L.B. c1997.. Rapport concernant l'assistance technique offerte à l'entreprise calédonienne de pêche thonière à la palangre Navimon: 19 août - 23 décembre 1996. Nouméa, Nouvelle-Calédonie: Commission du Pacifique Sud. vii, 34 p. :</dc:description>
          <dc:publisher>Commission du Pacifique Sud</dc:publisher>
          <dc:date>1997</dc:date>
          <dc:type>Text</dc:type>
          <dc:format>application/pdf</dc:format>
          <dc:identifier>http://www.spc.int/DigitalLibrary/Doc/FAME/Reports/Beverly_97_LonglineFishingNewCaledonia_VF.pdf</dc:identifier>
          <dc:language>fr</dc:language>
          <dc:coverage>New Caledonia</dc:coverage>
        </oai_dc:dc>
      </metadata>
    </record>
    <record>
      <header>
        <identifier>oai:www.spc.int:fb4dc9fd-8ace-474e-be17-fecd188e4773</identifier>
        <datestamp>2015-08-27T23:14:08Z</datestamp>
        <setSpec>All _LRF</setSpec>
        <setSpec>LRF_VF_2</setSpec>
        <setSpec>All_InfoBull</setSpec>
      </header>
      <metadata>
        <oai_dc:dc xmlns:oai_dc="http://www.openarchives.org/OAI/2.0/oai_dc/" xmlns:dc="http://purl.org/dc/elements/1.1/" xmlns:xsi="http://www.w3.org/2001/XMLSchema-instance" xsi:schemaLocation="http://www.openarchives.org/OAI/2.0/oai_dc/ http://www.openarchives.org/OAI/2.0/oai_dc.xsd">
          <dc:title>Un projet du Fonds mondial pour la nature sur la pêche au cyanure</dc:title>
          <dc:creator>Ruxton J.</dc:creator>
          <dc:description>Ruxton J. 1998. Un projet du Fonds mondial pour la nature sur la pêche au cyanure. Ressources marines et commercialisation, Bulletin d'information de la CPS 2:30-31.</dc:description>
          <dc:date>1998</dc:date>
          <dc:type>Text</dc:type>
          <dc:format>application/pdf</dc:format>
          <dc:identifier>http://www.spc.int/DigitalLibrary/Doc/FAME/InfoBull/LRF_VF/2/LRF2VF_30_Ruxton.pdf</dc:identifier>
          <dc:language>fr</dc:language>
        </oai_dc:dc>
      </metadata>
    </record>
    <record>
      <header>
        <identifier>oai:www.spc.int:12f2a790-ca5b-4aaf-8958-fed0bac1774a</identifier>
        <datestamp>2015-08-18T00:00:13Z</datestamp>
        <setSpec>All_InfoBull</setSpec>
        <setSpec>BDM_8</setSpec>
        <setSpec>All_BDM</setSpec>
      </header>
      <metadata>
        <oai_dc:dc xmlns:oai_dc="http://www.openarchives.org/OAI/2.0/oai_dc/" xmlns:dc="http://purl.org/dc/elements/1.1/" xmlns:xsi="http://www.w3.org/2001/XMLSchema-instance" xsi:schemaLocation="http://www.openarchives.org/OAI/2.0/oai_dc/ http://www.openarchives.org/OAI/2.0/oai_dc.xsd">
          <dc:title>Gamete dispersion and fertilisation success of the sea cucumber &lt;i&gt;Cucumaria frondosa&lt;/i&gt;</dc:title>
          <dc:creator>Hamel J.-F.</dc:creator>
          <dc:creator>Mercier A.</dc:creator>
          <dc:subject>Sea cucumbers</dc:subject>
          <dc:description>Hamel J.-F., Mercier A. 1996. Gamete dispersion and fertilisation success of the sea cucumber &lt;i&gt;Cucumaria frondosa&lt;/i&gt;. SPC Beche-de-mer Information Bulletin 8:34-40.</dc:description>
          <dc:date>1996</dc:date>
          <dc:type>Text</dc:type>
          <dc:format>application/pdf</dc:format>
          <dc:identifier>http://www.spc.int/DigitalLibrary/Doc/FAME/InfoBull/BDM/8/BDM8_34_Hamel.pdf</dc:identifier>
          <dc:language>en</dc:language>
        </oai_dc:dc>
      </metadata>
    </record>
    <record>
      <header>
        <identifier>oai:www.spc.int:fd87bd7b-f7e0-4a33-9ed4-fed5f3dbc040</identifier>
        <datestamp>2015-08-31T02:27:35Z</datestamp>
        <setSpec>All_InfoBull</setSpec>
        <setSpec>TRAD</setSpec>
        <setSpec>All_TRAD</setSpec>
      </header>
      <metadata>
        <oai_dc:dc xmlns:oai_dc="http://www.openarchives.org/OAI/2.0/oai_dc/" xmlns:dc="http://purl.org/dc/elements/1.1/" xmlns:xsi="http://www.w3.org/2001/XMLSchema-instance" xsi:schemaLocation="http://www.openarchives.org/OAI/2.0/oai_dc/ http://www.openarchives.org/OAI/2.0/oai_dc.xsd">
          <dc:title>SPC Traditional Marine Resource Management and Knowledge Information Bulletin #11 - September 1999</dc:title>
          <dc:creator>Anon.</dc:creator>
          <dc:subject>Fishery management</dc:subject>
          <dc:description>Anon. 1999. SPC Traditional Marine Resource Management and Knowledge Information Bulletin 11. Noumea, New Caledonia: Secretariat of the Pacific Community. 28 p.</dc:description>
          <dc:date>1999</dc:date>
          <dc:type>Text</dc:type>
          <dc:format>application/pdf</dc:format>
          <dc:identifier>http://www.spc.int/DigitalLibrary/Doc/FAME/InfoBull/TRAD/11/TRAD11.pdf</dc:identifier>
          <dc:language>en</dc:language>
        </oai_dc:dc>
      </metadata>
    </record>
    <record>
      <header>
        <identifier>oai:www.spc.int:08f1fe80-ee78-468a-b289-fed9a8569f90</identifier>
        <datestamp>2015-03-30T05:45:30Z</datestamp>
        <setSpec>All_Reports</setSpec>
      </header>
      <metadata>
        <oai_dc:dc xmlns:oai_dc="http://www.openarchives.org/OAI/2.0/oai_dc/" xmlns:dc="http://purl.org/dc/elements/1.1/" xmlns:xsi="http://www.w3.org/2001/XMLSchema-instance" xsi:schemaLocation="http://www.openarchives.org/OAI/2.0/oai_dc/ http://www.openarchives.org/OAI/2.0/oai_dc.xsd">
          <dc:title>Microalgae culture training for Tonga fisheries staff</dc:title>
          <dc:creator>Malimali S.</dc:creator>
          <dc:subject>Algae culture</dc:subject>
          <dc:subject>Fisheries</dc:subject>
          <dc:subject>Marine algae</dc:subject>
          <dc:description>Malimali S. 2010. Microalgae culture training for Tonga fisheries staff. [S.l.]: [s.n.]. 3 p.</dc:description>
          <dc:date>2010</dc:date>
          <dc:type>Text</dc:type>
          <dc:format>application/pdf</dc:format>
          <dc:identifier>http://www.spc.int/DigitalLibrary/Doc/FAME/Reports/ACIAR/ACIAR0502_Microalgae_culture_training_Tonga.pdf</dc:identifier>
          <dc:language>en</dc:language>
          <dc:coverage>Tonga</dc:coverage>
        </oai_dc:dc>
      </metadata>
    </record>
    <record>
      <header>
        <identifier>oai:www.spc.int:6b8c6646-e9aa-4f75-b2d6-fedeaec4da66</identifier>
        <datestamp>2017-11-02T00:00:59Z</datestamp>
        <setSpec>Brochures</setSpec>
      </header>
      <metadata>
        <oai_dc:dc xmlns:oai_dc="http://www.openarchives.org/OAI/2.0/oai_dc/" xmlns:dc="http://purl.org/dc/elements/1.1/" xmlns:xsi="http://www.w3.org/2001/XMLSchema-instance" xsi:schemaLocation="http://www.openarchives.org/OAI/2.0/oai_dc/ http://www.openarchives.org/OAI/2.0/oai_dc.xsd">
          <dc:title>Gaed long ol toksave blong ol fising komiuniti long Vanuatu - Leaflet 1: Ol tabu eria we komiuniti i manejmen olsem pat blong manejmen blong fiseris</dc:title>
          <dc:creator>Anon.</dc:creator>
          <dc:description>Anon. 2017. Gaed long ol toksave blong ol fising komiuniti long Vanuatu - Leaflet 1: Ol tabu eria we komiuniti i manejmen olsem pat blong manejmen blong fiseris.  Noumea, New Caledonia: Secretariat of the Pacific Community. 2 p.</dc:description>
          <dc:date>2017</dc:date>
          <dc:type>Text</dc:type>
          <dc:format>application/pdf</dc:format>
          <dc:identifier>http://www.spc.int/DigitalLibrary/Doc/FAME/Brochures/Anon_17_leaflet1_No_take_areas_bislama.pdf</dc:identifier>
          <dc:language>bi</dc:language>
          <dc:coverage>Vanuatu</dc:coverage>
        </oai_dc:dc>
      </metadata>
    </record>
    <record>
      <header>
        <identifier>oai:www.spc.int:adc3a7ed-c461-4475-80cd-feeafac0cb4b</identifier>
        <datestamp>2015-08-28T04:48:01Z</datestamp>
        <setSpec>All_InfoBull</setSpec>
        <setSpec>All_POIB</setSpec>
        <setSpec>POIB_2</setSpec>
      </header>
      <metadata>
        <oai_dc:dc xmlns:oai_dc="http://www.openarchives.org/OAI/2.0/oai_dc/" xmlns:dc="http://purl.org/dc/elements/1.1/" xmlns:xsi="http://www.w3.org/2001/XMLSchema-instance" xsi:schemaLocation="http://www.openarchives.org/OAI/2.0/oai_dc/ http://www.openarchives.org/OAI/2.0/oai_dc.xsd">
          <dc:title>Drafting a management plan in the Cook Islands</dc:title>
          <dc:creator>Dashwood J.</dc:creator>
          <dc:subject>Pearl oysters</dc:subject>
          <dc:description>Dashwood J. 1990. Drafting a management plan in the Cook Islands. SPC Pearl Oyster Information Bulletin 2:12.</dc:description>
          <dc:date>1990</dc:date>
          <dc:type>Text</dc:type>
          <dc:format>application/pdf</dc:format>
          <dc:identifier>http://www.spc.int/DigitalLibrary/Doc/FAME/InfoBull/POIB/2/POIB2_12_Das.pdf</dc:identifier>
          <dc:language>en</dc:language>
          <dc:coverage>Cook Islands</dc:coverage>
        </oai_dc:dc>
      </metadata>
    </record>
    <record>
      <header>
        <identifier>oai:www.spc.int:fa3d53a9-53a7-432c-8298-feeb30d5a759</identifier>
        <datestamp>2012-07-30T21:28:24Z</datestamp>
        <setSpec>All_Reports</setSpec>
      </header>
      <metadata>
        <oai_dc:dc xmlns:oai_dc="http://www.openarchives.org/OAI/2.0/oai_dc/" xmlns:dc="http://purl.org/dc/elements/1.1/" xmlns:xsi="http://www.w3.org/2001/XMLSchema-instance" xsi:schemaLocation="http://www.openarchives.org/OAI/2.0/oai_dc/ http://www.openarchives.org/OAI/2.0/oai_dc.xsd">
          <dc:title>Deepwater demersal fish</dc:title>
          <dc:creator>Moffitt R.B.</dc:creator>
          <dc:subject>Deep-sea fisheries</dc:subject>
          <dc:subject>Fishery resources</dc:subject>
          <dc:subject>Marine resources</dc:subject>
          <dc:description>Moffitt R.B. 1993. Deepwater demersal fish. p. 73-95. In: Wright A.,  Hills L. (eds). Nearshore marine resources of the South Pacific. Honiara / Suva: Forum Fisheries Agency / Institute of Pacific Studies.</dc:description>
          <dc:publisher>Forum Fisheries Agency (FFA)</dc:publisher>
          <dc:date>1993</dc:date>
          <dc:type>Text</dc:type>
          <dc:format>application/pdf</dc:format>
          <dc:identifier>http://www.spc.int/DigitalLibrary/Doc/FAME/Reports/Moffitt_93_DeepwaterDemersal.pdf</dc:identifier>
          <dc:language>en</dc:language>
        </oai_dc:dc>
      </metadata>
    </record>
    <record>
      <header>
        <identifier>oai:www.spc.int:5cf233a6-79ab-429a-a6de-feef87ac58ab</identifier>
        <datestamp>2015-08-19T04:42:46Z</datestamp>
        <setSpec>All_InfoBull</setSpec>
        <setSpec>All_BDM</setSpec>
        <setSpec>BDM_VF_10</setSpec>
      </header>
      <metadata>
        <oai_dc:dc xmlns:oai_dc="http://www.openarchives.org/OAI/2.0/oai_dc/" xmlns:dc="http://purl.org/dc/elements/1.1/" xmlns:xsi="http://www.w3.org/2001/XMLSchema-instance" xsi:schemaLocation="http://www.openarchives.org/OAI/2.0/oai_dc/ http://www.openarchives.org/OAI/2.0/oai_dc.xsd">
          <dc:title>Gestion durable de la filière holothuries à Madagascar</dc:title>
          <dc:creator>Conand C.</dc:creator>
          <dc:creator>De San M.</dc:creator>
          <dc:creator>Refeno G.</dc:creator>
          <dc:creator>Razafintseheno G.</dc:creator>
          <dc:creator>Mara E.</dc:creator>
          <dc:creator>Andriajatovo S.</dc:creator>
          <dc:subject>Sea cucumbers</dc:subject>
          <dc:description>Conand C., De San M., Refeno G., Razafintseheno G., Mara E., Andriajatovo S. 1998. Gestion durable de la filière holothuries à Madagascar. La Bêche-de-mer, Bulletin d'information de la CPS 10:8-10.</dc:description>
          <dc:date>1998</dc:date>
          <dc:type>Text</dc:type>
          <dc:format>application/pdf</dc:format>
          <dc:identifier>http://www.spc.int/DigitalLibrary/Doc/FAME/InfoBull/BDM_VF/10/BDM10VF_08_Conand.pdf</dc:identifier>
          <dc:language>fr</dc:language>
          <dc:coverage>Madagascar</dc:coverage>
        </oai_dc:dc>
      </metadata>
    </record>
    <record>
      <header>
        <identifier>oai:www.spc.int:967824fe-55b2-49ac-b657-fef33d06b323</identifier>
        <datestamp>2015-08-31T00:29:55Z</datestamp>
        <setSpec>POIB_VF_11</setSpec>
        <setSpec>All_POIB</setSpec>
        <setSpec>All_InfoBull</setSpec>
      </header>
      <metadata>
        <oai_dc:dc xmlns:oai_dc="http://www.openarchives.org/OAI/2.0/oai_dc/" xmlns:dc="http://purl.org/dc/elements/1.1/" xmlns:xsi="http://www.w3.org/2001/XMLSchema-instance" xsi:schemaLocation="http://www.openarchives.org/OAI/2.0/oai_dc/ http://www.openarchives.org/OAI/2.0/oai_dc.xsd">
          <dc:title>Observations relatives à l'impact de l'installation d'une ferme perlicole à Guaymas, État de Sonora (Mexique)</dc:title>
          <dc:creator>Arizmendi E.</dc:creator>
          <dc:subject>Pearl oysters</dc:subject>
          <dc:description>Arizmendi E. 1998. Observations relatives à l'impact de l'installation d'une ferme perlicole à Guaymas, État de Sonora (Mexique). L'Huître perlière, Bulletin d'information de la CPS 11:16.</dc:description>
          <dc:date>1998</dc:date>
          <dc:type>Text</dc:type>
          <dc:format>application/pdf</dc:format>
          <dc:identifier>http://www.spc.int/DigitalLibrary/Doc/FAME/InfoBull/POIB_VF/11/POIB11VF_16_Arizmendi.pdf</dc:identifier>
          <dc:language>fr</dc:language>
          <dc:coverage>Mexico</dc:coverage>
        </oai_dc:dc>
      </metadata>
    </record>
    <record>
      <header>
        <identifier>oai:www.spc.int:44cbbeca-0559-4d4c-879e-fef73b8a9e5b</identifier>
        <datestamp>2015-08-19T04:43:29Z</datestamp>
        <setSpec>All_InfoBull</setSpec>
        <setSpec>All_BDM</setSpec>
        <setSpec>BDM_VF_10</setSpec>
      </header>
      <metadata>
        <oai_dc:dc xmlns:oai_dc="http://www.openarchives.org/OAI/2.0/oai_dc/" xmlns:dc="http://purl.org/dc/elements/1.1/" xmlns:xsi="http://www.w3.org/2001/XMLSchema-instance" xsi:schemaLocation="http://www.openarchives.org/OAI/2.0/oai_dc/ http://www.openarchives.org/OAI/2.0/oai_dc.xsd">
          <dc:title>Notes préliminaires sur l'exploitation des holothuries dans la nouvelle réserve marine nationale de Wakatobi, Sulawesi (Indonésie)</dc:title>
          <dc:creator>Moore A.</dc:creator>
          <dc:subject>Sea cucumbers</dc:subject>
          <dc:description>Moore A. 1998. Notes préliminaires sur l'exploitation des holothuries dans la nouvelle réserve marine nationale de Wakatobi, Sulawesi (Indonésie). La Bêche-de-mer, Bulletin d'information de la CPS 10:31-34.</dc:description>
          <dc:date>1998</dc:date>
          <dc:type>Text</dc:type>
          <dc:format>application/pdf</dc:format>
          <dc:identifier>http://www.spc.int/DigitalLibrary/Doc/FAME/InfoBull/BDM_VF/10/BDM10VF_31_Moore.pdf</dc:identifier>
          <dc:language>fr</dc:language>
          <dc:coverage>Indonesia</dc:coverage>
        </oai_dc:dc>
      </metadata>
    </record>
    <record>
      <header>
        <identifier>oai:www.spc.int:80093c6a-2222-4572-9ff8-fef93f8ef77a</identifier>
        <datestamp>2015-08-17T23:22:32Z</datestamp>
        <setSpec>All_InfoBull</setSpec>
        <setSpec>All_BDM</setSpec>
        <setSpec>BDM_14</setSpec>
      </header>
      <metadata>
        <oai_dc:dc xmlns:oai_dc="http://www.openarchives.org/OAI/2.0/oai_dc/" xmlns:dc="http://purl.org/dc/elements/1.1/" xmlns:xsi="http://www.w3.org/2001/XMLSchema-instance" xsi:schemaLocation="http://www.openarchives.org/OAI/2.0/oai_dc/ http://www.openarchives.org/OAI/2.0/oai_dc.xsd">
          <dc:title>Review of sandfish breeding and rearing methods</dc:title>
          <dc:creator>Pitt R.</dc:creator>
          <dc:subject>Sea cucumbers</dc:subject>
          <dc:description>Pitt R. 2001. Review of sandfish breeding and rearing methods. SPC Beche-de-mer Information Bulletin 14:14-21.</dc:description>
          <dc:date>2001</dc:date>
          <dc:type>Text</dc:type>
          <dc:format>application/pdf</dc:format>
          <dc:identifier>http://www.spc.int/DigitalLibrary/Doc/FAME/InfoBull/BDM/14/BDM14_14_Pitt.pdf</dc:identifier>
          <dc:language>en</dc:language>
        </oai_dc:dc>
      </metadata>
    </record>
    <record>
      <header>
        <identifier>oai:www.spc.int:06040dd3-c6bc-4510-965f-fef9d5ab7f88</identifier>
        <datestamp>2012-07-30T21:28:24Z</datestamp>
        <setSpec>All_Meetings</setSpec>
        <setSpec>RTMF_24</setSpec>
      </header>
      <metadata>
        <oai_dc:dc xmlns:oai_dc="http://www.openarchives.org/OAI/2.0/oai_dc/" xmlns:dc="http://purl.org/dc/elements/1.1/" xmlns:xsi="http://www.w3.org/2001/XMLSchema-instance" xsi:schemaLocation="http://www.openarchives.org/OAI/2.0/oai_dc/ http://www.openarchives.org/OAI/2.0/oai_dc.xsd">
          <dc:title>Certificat d'homme de pont pour les membres d'équipage des bâteaux de pêche opérant dans le pacifique sud : considérations préliminaires</dc:title>
          <dc:creator>Anon.</dc:creator>
          <dc:subject>Fisheries</dc:subject>
          <dc:subject>Fishery management</dc:subject>
          <dc:description>Anon. 1992. Certificat d'homme de pont pour les membres d'équipage des bâteaux de pêche opérant dans le pacifique sud : considérations préliminaires [WP 7]. Nouméa, Nouvelle-Calédonie: Commission du Pacifique Sud. Vingt-Quatrième Conférence Technique Régionale sur les Pêches. 6 p.</dc:description>
          <dc:publisher>Commission du Pacifique Sud</dc:publisher>
          <dc:date>1992</dc:date>
          <dc:type>Text</dc:type>
          <dc:format>application/pdf</dc:format>
          <dc:identifier>http://www.spc.int/DigitalLibrary/Doc/FAME/Meetings/RTMF/24/WP7_VF.PDF</dc:identifier>
          <dc:language>fr</dc:language>
        </oai_dc:dc>
      </metadata>
    </record>
    <record>
      <header>
        <identifier>oai:www.spc.int:8ad3c8c5-252a-4a42-a5ff-ff002302843a</identifier>
        <datestamp>2015-03-30T06:06:18Z</datestamp>
        <setSpec>All_Meetings</setSpec>
        <setSpec>FFA</setSpec>
        <setSpec>SPC_FFA_1995</setSpec>
      </header>
      <metadata>
        <oai_dc:dc xmlns:oai_dc="http://www.openarchives.org/OAI/2.0/oai_dc/" xmlns:dc="http://purl.org/dc/elements/1.1/" xmlns:xsi="http://www.w3.org/2001/XMLSchema-instance" xsi:schemaLocation="http://www.openarchives.org/OAI/2.0/oai_dc/ http://www.openarchives.org/OAI/2.0/oai_dc.xsd">
          <dc:title>Research and management of the industrial prawn fishery of the Gulf of Papua</dc:title>
          <dc:creator>Evans C.R.</dc:creator>
          <dc:creator>Kare B.D.</dc:creator>
          <dc:creator>Opnai L.J.</dc:creator>
          <dc:subject>Fisheries</dc:subject>
          <dc:subject>Shrimp fisheries</dc:subject>
          <dc:description>Evans C.R., Kare B.D., Opnai L.J. 1995. Research and management of the industrial prawn fishery of the Gulf of Papua [BP 28]. Noumea, New Caledonia: South Pacific Commission. South Pacific Commission and Forum Fisheries Agency Workshop on the Management of South Pacific Inshore Fisheries,  Noumea, New Caledonia, 1995. 34 p.</dc:description>
          <dc:publisher>South Pacific Commission</dc:publisher>
          <dc:date>1995</dc:date>
          <dc:type>Text</dc:type>
          <dc:format>application/pdf</dc:format>
          <dc:identifier>http://www.spc.int/DigitalLibrary/Doc/FAME/Meetings/SPC_FFA_Workshop_1995/BP28.pdf</dc:identifier>
          <dc:language>en</dc:language>
          <dc:coverage>Papua New Guinea</dc:coverage>
        </oai_dc:dc>
      </metadata>
    </record>
    <record>
      <header>
        <identifier>oai:www.spc.int:e0465c9b-9162-405f-9fd0-ff14200f069b</identifier>
        <datestamp>2012-07-30T21:28:24Z</datestamp>
        <setSpec>All_Meetings</setSpec>
        <setSpec>FishMan_1998</setSpec>
      </header>
      <metadata>
        <oai_dc:dc xmlns:oai_dc="http://www.openarchives.org/OAI/2.0/oai_dc/" xmlns:dc="http://purl.org/dc/elements/1.1/" xmlns:xsi="http://www.w3.org/2001/XMLSchema-instance" xsi:schemaLocation="http://www.openarchives.org/OAI/2.0/oai_dc/ http://www.openarchives.org/OAI/2.0/oai_dc.xsd">
          <dc:title>Developing inshore sportfishing in Palau</dc:title>
          <dc:creator>Idechong N.</dc:creator>
          <dc:creator>Graham T.</dc:creator>
          <dc:subject>Fishing</dc:subject>
          <dc:description>Idechong N., Graham T. 1998. Developing inshore sportfishing in Palau [BP 19]. Noumea, New Caledonia: Secretariat of the Pacific Community. Pacific Community Fisheries Management Workshop, Noumea, New Caledonia, 12-16 October 1998, 2nd. 10 p.</dc:description>
          <dc:publisher>Secretariat of the Pacific Community</dc:publisher>
          <dc:date>1998</dc:date>
          <dc:type>Text</dc:type>
          <dc:format>application/pdf</dc:format>
          <dc:identifier>http://www.spc.int/DigitalLibrary/Doc/FAME/Meetings/SPC_FishMan_Workshop_1998/BP19.pdf</dc:identifier>
          <dc:language>en</dc:language>
          <dc:coverage>Palau</dc:coverage>
        </oai_dc:dc>
      </metadata>
    </record>
    <record>
      <header>
        <identifier>oai:www.spc.int:674d0cc5-7e0a-4ea9-812b-ff146a7a192d</identifier>
        <datestamp>2015-09-02T00:08:44Z</datestamp>
        <setSpec>All_InfoBull</setSpec>
        <setSpec>TROC_VF_12</setSpec>
        <setSpec>All_TROC</setSpec>
      </header>
      <metadata>
        <oai_dc:dc xmlns:oai_dc="http://www.openarchives.org/OAI/2.0/oai_dc/" xmlns:dc="http://purl.org/dc/elements/1.1/" xmlns:xsi="http://www.w3.org/2001/XMLSchema-instance" xsi:schemaLocation="http://www.openarchives.org/OAI/2.0/oai_dc/ http://www.openarchives.org/OAI/2.0/oai_dc.xsd">
          <dc:title>La nature nous donne une leçon de conception des armures</dc:title>
          <dc:creator>Anon.</dc:creator>
          <dc:subject>Trochus niloticus</dc:subject>
          <dc:description>Anon. 2006. La nature nous donne une leçon de conception des armures. Le Troca, Bulletin d'information de la CPS 12:27.</dc:description>
          <dc:date>2006</dc:date>
          <dc:type>Text</dc:type>
          <dc:format>application/pdf</dc:format>
          <dc:identifier>http://www.spc.int/DigitalLibrary/Doc/FAME/InfoBull/TROC_VF/12/TROC12VF_27_Nature.pdf</dc:identifier>
          <dc:language>fr</dc:language>
        </oai_dc:dc>
      </metadata>
    </record>
    <record>
      <header>
        <identifier>oai:www.spc.int:68dff178-8a5d-4ea2-970b-ff1e2d80032d</identifier>
        <datestamp>2015-08-27T21:43:26Z</datestamp>
        <setSpec>All_BDM</setSpec>
        <setSpec>All_InfoBull</setSpec>
        <setSpec>BDM_VF</setSpec>
      </header>
      <metadata>
        <oai_dc:dc xmlns:oai_dc="http://www.openarchives.org/OAI/2.0/oai_dc/" xmlns:dc="http://purl.org/dc/elements/1.1/" xmlns:xsi="http://www.w3.org/2001/XMLSchema-instance" xsi:schemaLocation="http://www.openarchives.org/OAI/2.0/oai_dc/ http://www.openarchives.org/OAI/2.0/oai_dc.xsd">
          <dc:title>La Bêche-de-mer, Bulletin d'information de la CPS n°33 - Août 2013</dc:title>
          <dc:creator>Anon.</dc:creator>
          <dc:subject>Sea cucumbers</dc:subject>
          <dc:description>Anon. 2013. La Bêche-de-mer, Bulletin d'information de la CPS 33. Nouméa, Nouvelle-Calédonie : Secrétariat Général de la Communauté du Pacifique. 72 p.</dc:description>
          <dc:date>2013</dc:date>
          <dc:type>Text</dc:type>
          <dc:format>application/pdf</dc:format>
          <dc:identifier>http://www.spc.int/DigitalLibrary/Doc/FAME/InfoBull/BDM_VF/33/BDM33VF.pdf</dc:identifier>
          <dc:language>fr</dc:language>
        </oai_dc:dc>
      </metadata>
    </record>
    <record>
      <header>
        <identifier>oai:www.spc.int:2de9ae23-9417-4a12-af91-ff27c0156f6f</identifier>
        <datestamp>2012-07-30T21:28:24Z</datestamp>
        <setSpec>All_Reports</setSpec>
        <setSpec>management</setSpec>
      </header>
      <metadata>
        <oai_dc:dc xmlns:oai_dc="http://www.openarchives.org/OAI/2.0/oai_dc/" xmlns:dc="http://purl.org/dc/elements/1.1/" xmlns:xsi="http://www.w3.org/2001/XMLSchema-instance" xsi:schemaLocation="http://www.openarchives.org/OAI/2.0/oai_dc/ http://www.openarchives.org/OAI/2.0/oai_dc.xsd">
          <dc:title>Commonwealth of the Northern Mariana Islands Aquaculture Development Plan 2011–2015</dc:title>
          <dc:creator>Anon.</dc:creator>
          <dc:subject>Aquaculture</dc:subject>
          <dc:description>Anon. 2011. Commonwealth of the Northern Mariana Islands Aquaculture Development Plan 2011–2015. Noumea, New Caledonia: Secretariat of the Pacific Community. 32 p.</dc:description>
          <dc:date>2011</dc:date>
          <dc:type>Text</dc:type>
          <dc:format>application/pdf</dc:format>
          <dc:identifier>http://www.spc.int/DigitalLibrary/Doc/FAME/Reports/Anon_11_CNMI_Aquaculture_Plan.pdf</dc:identifier>
          <dc:language>en</dc:language>
          <dc:coverage>Northern Mariana Islands</dc:coverage>
        </oai_dc:dc>
      </metadata>
    </record>
    <record>
      <header>
        <identifier>oai:www.spc.int:1c605208-834b-4af7-ae16-ff2b4eefe4e2</identifier>
        <datestamp>2012-07-30T21:28:24Z</datestamp>
        <setSpec>All_Meetings</setSpec>
        <setSpec>RTMF_16</setSpec>
      </header>
      <metadata>
        <oai_dc:dc xmlns:oai_dc="http://www.openarchives.org/OAI/2.0/oai_dc/" xmlns:dc="http://purl.org/dc/elements/1.1/" xmlns:xsi="http://www.w3.org/2001/XMLSchema-instance" xsi:schemaLocation="http://www.openarchives.org/OAI/2.0/oai_dc/ http://www.openarchives.org/OAI/2.0/oai_dc.xsd">
          <dc:title>Ten years boat development in the South Pacific - What can we learn from it?</dc:title>
          <dc:creator>Gulbrandsen O.</dc:creator>
          <dc:subject>Fisheries</dc:subject>
          <dc:subject>Fishing boats</dc:subject>
          <dc:description>Gulbrandsen O. 1984. Ten years boat development in the South Pacific - What can we learn from it? [WP 14]. Noumea, New Caledonia: South Pacific Commission. Regional Technical Meeting on Fisheries, Noumea, New Caledonia, 13-17 August 1984, 16th. 12 p.</dc:description>
          <dc:publisher>South Pacific Commission</dc:publisher>
          <dc:date>1984</dc:date>
          <dc:type>Text</dc:type>
          <dc:format>application/pdf</dc:format>
          <dc:identifier>http://www.spc.int/DigitalLibrary/Doc/FAME/Meetings/RTMF/16/WP14.pdf</dc:identifier>
          <dc:language>en</dc:language>
        </oai_dc:dc>
      </metadata>
    </record>
    <record>
      <header>
        <identifier>oai:www.spc.int:04e589fa-5a1f-478b-9aee-ff44b700f0e9</identifier>
        <datestamp>2012-07-30T21:28:24Z</datestamp>
        <setSpec>All_Meetings</setSpec>
        <setSpec>SPC_FFA_1995</setSpec>
        <setSpec>FFA</setSpec>
      </header>
      <metadata>
        <oai_dc:dc xmlns:oai_dc="http://www.openarchives.org/OAI/2.0/oai_dc/" xmlns:dc="http://purl.org/dc/elements/1.1/" xmlns:xsi="http://www.w3.org/2001/XMLSchema-instance" xsi:schemaLocation="http://www.openarchives.org/OAI/2.0/oai_dc/ http://www.openarchives.org/OAI/2.0/oai_dc.xsd">
          <dc:title>La réglementation relative à la protection des ressources halieutiques cotières et le projet de repeuplement à Okinawa</dc:title>
          <dc:creator>Isa. J.</dc:creator>
          <dc:subject>Fishery management</dc:subject>
          <dc:description>Isa. J. 1995. La réglementation relative à la protection des ressources halieutiques cotières et le projet de repeuplement à Okinawa  [Doc. réf. 16A]. Noumea, New Caledonia: South Pacific Commission. South Pacific Commission and Forum Fisheries Agency Workshop on the Management of South Pacific Inshore Fisheries,  Noumea, New Caledonia, 1995. 1 p.</dc:description>
          <dc:publisher>South Pacific Commission</dc:publisher>
          <dc:date>1995</dc:date>
          <dc:type>Text</dc:type>
          <dc:format>application/pdf</dc:format>
          <dc:identifier>http://www.spc.int/DigitalLibrary/Doc/FAME/Meetings/SPC_FFA_Workshop_1995/BP16_VF.pdf</dc:identifier>
          <dc:language>fr</dc:language>
          <dc:coverage>Japan</dc:coverage>
        </oai_dc:dc>
      </metadata>
    </record>
    <record>
      <header>
        <identifier>oai:www.spc.int:60a75c16-52e7-4b19-9a72-ff4746c1d1d0</identifier>
        <datestamp>2015-08-28T00:16:34Z</datestamp>
        <setSpec>All _LRF</setSpec>
        <setSpec>All_InfoBull</setSpec>
        <setSpec>LRF_VF</setSpec>
      </header>
      <metadata>
        <oai_dc:dc xmlns:oai_dc="http://www.openarchives.org/OAI/2.0/oai_dc/" xmlns:dc="http://purl.org/dc/elements/1.1/" xmlns:xsi="http://www.w3.org/2001/XMLSchema-instance" xsi:schemaLocation="http://www.openarchives.org/OAI/2.0/oai_dc/ http://www.openarchives.org/OAI/2.0/oai_dc.xsd">
          <dc:title>Ressources marines et commercialisation, Bulletin d'information de la CPS n°8 - Octobre 2001</dc:title>
          <dc:creator>Anon.</dc:creator>
          <dc:description>Anon. 2001. Ressources marines et commercialisation, Bulletin d'information de la CPS 8. Nouméa, Nouvelle-Calédonie : Secrétariat Général de la Communauté du Pacifique. 40 p.</dc:description>
          <dc:date>2001</dc:date>
          <dc:type>Text</dc:type>
          <dc:format>application/pdf</dc:format>
          <dc:identifier>http://www.spc.int/DigitalLibrary/Doc/FAME/InfoBull/LRF_VF/8/LRF8VF.pdf</dc:identifier>
          <dc:language>fr</dc:language>
        </oai_dc:dc>
      </metadata>
    </record>
    <record>
      <header>
        <identifier>oai:www.spc.int:78be60d1-b9a7-40c1-927a-ff51856d26f9</identifier>
        <datestamp>2015-08-20T21:42:50Z</datestamp>
        <setSpec>All _LRF</setSpec>
        <setSpec>All_InfoBull</setSpec>
        <setSpec>LRF_5</setSpec>
      </header>
      <metadata>
        <oai_dc:dc xmlns:oai_dc="http://www.openarchives.org/OAI/2.0/oai_dc/" xmlns:dc="http://purl.org/dc/elements/1.1/" xmlns:xsi="http://www.w3.org/2001/XMLSchema-instance" xsi:schemaLocation="http://www.openarchives.org/OAI/2.0/oai_dc/ http://www.openarchives.org/OAI/2.0/oai_dc.xsd">
          <dc:title>Regional cooperation in grouper aquaculture research moves forward - A new research network formed</dc:title>
          <dc:creator>Rimmer M.</dc:creator>
          <dc:creator>Williams K.C.</dc:creator>
          <dc:creator>Phillips M.J.</dc:creator>
          <dc:creator>Kongkeo H.</dc:creator>
          <dc:subject>Aquaculture</dc:subject>
          <dc:description>Rimmer M., Williams K.C., Phillips M.J., Kongkeo H. 1999. Regional cooperation in grouper aquaculture research moves forward - A new research network formed. SPC Live Reef Fish Information Bulletin 5:36-38.</dc:description>
          <dc:date>1999</dc:date>
          <dc:type>Text</dc:type>
          <dc:format>application/pdf</dc:format>
          <dc:identifier>http://www.spc.int/DigitalLibrary/Doc/FAME/InfoBull/LRF/5/LRF5_36_Rimmer.pdf</dc:identifier>
          <dc:language>en</dc:language>
        </oai_dc:dc>
      </metadata>
    </record>
    <record>
      <header>
        <identifier>oai:www.spc.int:f05e03f0-3a51-48f6-b9a5-ff54d2827ddd</identifier>
        <datestamp>2015-08-20T05:21:19Z</datestamp>
        <setSpec>FishNews_132</setSpec>
        <setSpec>All_InfoBull</setSpec>
        <setSpec>All_FishNews</setSpec>
      </header>
      <metadata>
        <oai_dc:dc xmlns:oai_dc="http://www.openarchives.org/OAI/2.0/oai_dc/" xmlns:dc="http://purl.org/dc/elements/1.1/" xmlns:xsi="http://www.w3.org/2001/XMLSchema-instance" xsi:schemaLocation="http://www.openarchives.org/OAI/2.0/oai_dc/ http://www.openarchives.org/OAI/2.0/oai_dc.xsd">
          <dc:title>Global Aquaculture Conference and FAO COFI Sub-committee Meeting on Aquaculture in Thailand</dc:title>
          <dc:creator>Pickering T.</dc:creator>
          <dc:subject>Aquaculture</dc:subject>
          <dc:description>Pickering T. 2010. Global Aquaculture Conference and FAO COFI Sub-committee Meeting on Aquaculture in Thailand. SPC Fisheries Newsletter 132:22-23.</dc:description>
          <dc:date>2010</dc:date>
          <dc:type>Text</dc:type>
          <dc:format>application/pdf</dc:format>
          <dc:identifier>http://www.spc.int/DigitalLibrary/Doc/FAME/InfoBull/FishNews/132/FishNews132_22_Pickering.pdf</dc:identifier>
          <dc:language>en</dc:language>
          <dc:coverage>Thailand</dc:coverage>
        </oai_dc:dc>
      </metadata>
    </record>
    <record>
      <header>
        <identifier>oai:www.spc.int:37f86e56-8388-4838-8fa4-ff5bc9135c86</identifier>
        <datestamp>2012-07-30T21:28:24Z</datestamp>
        <setSpec>SPB_VF</setSpec>
        <setSpec>All_InfoBull</setSpec>
      </header>
      <metadata>
        <oai_dc:dc xmlns:oai_dc="http://www.openarchives.org/OAI/2.0/oai_dc/" xmlns:dc="http://purl.org/dc/elements/1.1/" xmlns:xsi="http://www.w3.org/2001/XMLSchema-instance" xsi:schemaLocation="http://www.openarchives.org/OAI/2.0/oai_dc/ http://www.openarchives.org/OAI/2.0/oai_dc.xsd">
          <dc:title>Recherche scientifique et pêche du thon auprès des territoires français du Pacifique Sud</dc:title>
          <dc:creator>Angot M.</dc:creator>
          <dc:subject>Tuna fisheries</dc:subject>
          <dc:description>Angot M. 1959. Recherche scientifique et pêche du thon auprès des territoires français du Pacifique Sud. Nouméa, Nouvelle-Calédonie: Commission du Pacifique Sud. Bulletin trimestriel Vol. 9, No. 4, octobre 1959, p. 33-48</dc:description>
          <dc:publisher>Commission du Pacifique Sud</dc:publisher>
          <dc:date>1959</dc:date>
          <dc:type>Text</dc:type>
          <dc:format>application/pdf</dc:format>
          <dc:identifier>http://www.spc.int/DigitalLibrary/Doc/FAME/InfoBull/SPB_VF/SPB9_4_Angot_VF.pdf</dc:identifier>
          <dc:language>fr</dc:language>
        </oai_dc:dc>
      </metadata>
    </record>
    <record>
      <header>
        <identifier>oai:www.spc.int:4fd35839-087a-4626-ad50-ff752156cfd4</identifier>
        <datestamp>2015-08-27T23:08:57Z</datestamp>
        <setSpec>LRF_VF_2</setSpec>
        <setSpec>All _LRF</setSpec>
        <setSpec>All_InfoBull</setSpec>
      </header>
      <metadata>
        <oai_dc:dc xmlns:oai_dc="http://www.openarchives.org/OAI/2.0/oai_dc/" xmlns:dc="http://purl.org/dc/elements/1.1/" xmlns:xsi="http://www.w3.org/2001/XMLSchema-instance" xsi:schemaLocation="http://www.openarchives.org/OAI/2.0/oai_dc/ http://www.openarchives.org/OAI/2.0/oai_dc.xsd">
          <dc:title>Mesures prises par Hong Kong dans le domaine de la pêche de poissons vivants destinés au marché de la restauration</dc:title>
          <dc:creator>Leung S.F.</dc:creator>
          <dc:description>Leung S.F. 1998. Mesures prises par Hong Kong dans le domaine de la pêche de poissons vivants destinés au marché de la restauration. Ressources marines et commercialisation, Bulletin d'information de la CPS 2:3-4.</dc:description>
          <dc:date>1998</dc:date>
          <dc:type>Text</dc:type>
          <dc:format>application/pdf</dc:format>
          <dc:identifier>http://www.spc.int/DigitalLibrary/Doc/FAME/InfoBull/LRF_VF/2/LRF2VF_03_Leung.pdf</dc:identifier>
          <dc:language>fr</dc:language>
          <dc:coverage>Hong Kong</dc:coverage>
        </oai_dc:dc>
      </metadata>
    </record>
    <record>
      <header>
        <identifier>oai:www.spc.int:138276f8-d226-47c5-ba68-ff7ac85f91df</identifier>
        <datestamp>2015-03-30T06:17:43Z</datestamp>
        <setSpec>All_Meetings</setSpec>
        <setSpec>WCPFC_SC8</setSpec>
      </header>
      <metadata>
        <oai_dc:dc xmlns:oai_dc="http://www.openarchives.org/OAI/2.0/oai_dc/" xmlns:dc="http://purl.org/dc/elements/1.1/" xmlns:xsi="http://www.w3.org/2001/XMLSchema-instance" xsi:schemaLocation="http://www.openarchives.org/OAI/2.0/oai_dc/ http://www.openarchives.org/OAI/2.0/oai_dc.xsd">
          <dc:title>Status of observer data management</dc:title>
          <dc:creator>Anon.</dc:creator>
          <dc:subject>Fisheries</dc:subject>
          <dc:subject>Tuna fisheries</dc:subject>
          <dc:description>Anon. 2012. Status of observer data management [ST-IP-02]. [Pohnpei, Federated States of Micronesia]: Western and Central Pacific Fisheries Commission (WCPFC). Scientific Committee Regular Session, Busan, Republic of Korea, 7-15 August 2012, 8th. 34 p.</dc:description>
          <dc:date>2012</dc:date>
          <dc:type>Text</dc:type>
          <dc:format>application/pdf</dc:format>
          <dc:identifier>http://www.spc.int/DigitalLibrary/Doc/FAME/Meetings/WCPFC/SC8/ST-IP-02.pdf</dc:identifier>
        </oai_dc:dc>
      </metadata>
    </record>
    <record>
      <header>
        <identifier>oai:www.spc.int:1052bf1b-6b55-4369-800d-ff9bc80d167c</identifier>
        <datestamp>2015-08-27T22:18:17Z</datestamp>
        <setSpec>FishNews_VF</setSpec>
        <setSpec>All_InfoBull</setSpec>
        <setSpec>All_FishNews</setSpec>
      </header>
      <metadata>
        <oai_dc:dc xmlns:oai_dc="http://www.openarchives.org/OAI/2.0/oai_dc/" xmlns:dc="http://purl.org/dc/elements/1.1/" xmlns:xsi="http://www.w3.org/2001/XMLSchema-instance" xsi:schemaLocation="http://www.openarchives.org/OAI/2.0/oai_dc/ http://www.openarchives.org/OAI/2.0/oai_dc.xsd">
          <dc:title>Lettre d'information sur les pêches de la CPS n°136 - Septembre/Décembre 2011</dc:title>
          <dc:creator>Anon.</dc:creator>
          <dc:subject>Fisheries</dc:subject>
          <dc:description>Anon. 2012. Lettre d'information sur les pêches de la CPS 136. Nouméa, Nouvelle-Calédonie : Secrétariat Général de la Communauté du Pacifique. 48 p.</dc:description>
          <dc:date>2012</dc:date>
          <dc:type>Text</dc:type>
          <dc:format>application/pdf</dc:format>
          <dc:identifier>http://www.spc.int/DigitalLibrary/Doc/FAME/InfoBull/FishNews_VF/136/FishNews136_VF.pdf</dc:identifier>
          <dc:language>fr</dc:language>
        </oai_dc:dc>
      </metadata>
    </record>
    <record>
      <header>
        <identifier>oai:www.spc.int:222d110f-e4c4-474c-9763-ff9cc670c868</identifier>
        <datestamp>2015-08-18T00:26:33Z</datestamp>
        <setSpec>BDM_2</setSpec>
        <setSpec>All_BDM</setSpec>
        <setSpec>All_InfoBull</setSpec>
      </header>
      <metadata>
        <oai_dc:dc xmlns:oai_dc="http://www.openarchives.org/OAI/2.0/oai_dc/" xmlns:dc="http://purl.org/dc/elements/1.1/" xmlns:xsi="http://www.w3.org/2001/XMLSchema-instance" xsi:schemaLocation="http://www.openarchives.org/OAI/2.0/oai_dc/ http://www.openarchives.org/OAI/2.0/oai_dc.xsd">
          <dc:title>Sea cucumber research in Washington State</dc:title>
          <dc:creator>Bradbury A.</dc:creator>
          <dc:subject>Sea cucumbers</dc:subject>
          <dc:description>Bradbury A. 1990. Sea cucumber research in Washington State. SPC Beche-de-mer Information Bulletin 2:11-12.</dc:description>
          <dc:date>1990</dc:date>
          <dc:type>Text</dc:type>
          <dc:format>application/pdf</dc:format>
          <dc:identifier>http://www.spc.int/DigitalLibrary/Doc/FAME/InfoBull/BDM/2/BDM2_11_Bradbury.pdf</dc:identifier>
          <dc:language>en</dc:language>
          <dc:coverage>United States</dc:coverage>
        </oai_dc:dc>
      </metadata>
    </record>
    <record>
      <header>
        <identifier>oai:www.spc.int:37b135b9-28c5-47ce-b5ab-ffb2dc23bbd3</identifier>
        <datestamp>2015-08-27T22:17:35Z</datestamp>
        <setSpec>All_InfoBull</setSpec>
        <setSpec>All_FishNews</setSpec>
        <setSpec>FishNews_VF</setSpec>
      </header>
      <metadata>
        <oai_dc:dc xmlns:oai_dc="http://www.openarchives.org/OAI/2.0/oai_dc/" xmlns:dc="http://purl.org/dc/elements/1.1/" xmlns:xsi="http://www.w3.org/2001/XMLSchema-instance" xsi:schemaLocation="http://www.openarchives.org/OAI/2.0/oai_dc/ http://www.openarchives.org/OAI/2.0/oai_dc.xsd">
          <dc:title>Lettre d'information sur les pêches de la CPS n°132 - Mai/Août 2010</dc:title>
          <dc:creator>Anon.</dc:creator>
          <dc:subject>Fisheries</dc:subject>
          <dc:description>Anon. 2010. Lettre d'information sur les pêches de la CPS 132. Nouméa, Nouvelle-Calédonie : Secrétariat Général de la Communauté du Pacifique. 36 p.</dc:description>
          <dc:date>2010</dc:date>
          <dc:type>Text</dc:type>
          <dc:format>application/pdf</dc:format>
          <dc:identifier>http://www.spc.int/DigitalLibrary/Doc/FAME/InfoBull/FishNews_VF/132/FishNews132VF.pdf</dc:identifier>
          <dc:language>fr</dc:language>
        </oai_dc:dc>
      </metadata>
    </record>
    <record>
      <header>
        <identifier>oai:www.spc.int:9fc78726-fea9-4811-a5a0-ffb39749c825</identifier>
        <datestamp>2015-08-30T21:53:41Z</datestamp>
        <setSpec>All_POIB</setSpec>
        <setSpec>POIB_5</setSpec>
        <setSpec>All_InfoBull</setSpec>
      </header>
      <metadata>
        <oai_dc:dc xmlns:oai_dc="http://www.openarchives.org/OAI/2.0/oai_dc/" xmlns:dc="http://purl.org/dc/elements/1.1/" xmlns:xsi="http://www.w3.org/2001/XMLSchema-instance" xsi:schemaLocation="http://www.openarchives.org/OAI/2.0/oai_dc/ http://www.openarchives.org/OAI/2.0/oai_dc.xsd">
          <dc:title>Pearl dealer's concern: Are consumers sated or just short of cash?</dc:title>
          <dc:creator>Shor R.</dc:creator>
          <dc:subject>Pearl oysters</dc:subject>
          <dc:description>Shor R. 1992. Pearl Dealer's concern: Are consumers sated or just short of cash? SPC Pearl Oyster Information Bulletin 5:25-27.</dc:description>
          <dc:date>1992</dc:date>
          <dc:type>Text</dc:type>
          <dc:format>application/pdf</dc:format>
          <dc:identifier>http://www.spc.int/DigitalLibrary/Doc/FAME/InfoBull/POIB/5/POIB5_25_Sho.pdf</dc:identifier>
          <dc:language>en</dc:language>
        </oai_dc:dc>
      </metadata>
    </record>
    <record>
      <header>
        <identifier>oai:www.spc.int:97a0a435-a61d-4760-aa91-ffc4ec82dc8b</identifier>
        <datestamp>2014-03-20T22:42:23Z</datestamp>
        <setSpec>Brochures</setSpec>
      </header>
      <metadata>
        <oai_dc:dc xmlns:oai_dc="http://www.openarchives.org/OAI/2.0/oai_dc/" xmlns:dc="http://purl.org/dc/elements/1.1/" xmlns:xsi="http://www.w3.org/2001/XMLSchema-instance" xsi:schemaLocation="http://www.openarchives.org/OAI/2.0/oai_dc/ http://www.openarchives.org/OAI/2.0/oai_dc.xsd">
          <dc:title>Na veitukutuku eso ka baleta na nodra veiqaravi na veikorokoro ena maroroi ni nodra iqoliqoli</dc:title>
          <dc:creator>Anon.</dc:creator>
          <dc:description>Anon. 2014. Na veitukutuku eso ka baleta na nodra veiqaravi na veikorokoro ena maroroi ni nodra iqoliqoli. Noumea, New Caledonia: Secretariat of the Pacific Community. 20 p. [in Fijian]</dc:description>
          <dc:date>2014</dc:date>
          <dc:type>Text</dc:type>
          <dc:format>application/pdf</dc:format>
          <dc:identifier>http://www.spc.int/DigitalLibrary/Doc/FAME/Brochures/Anon_14_ISFC_00_Guide_FJ.pdf.pdf</dc:identifier>
          <dc:language>fj</dc:language>
          <dc:coverage>Fiji</dc:coverage>
        </oai_dc:dc>
      </metadata>
    </record>
    <record>
      <header>
        <identifier>oai:www.spc.int:4121bd85-9840-4743-8f89-ffc63eff2d35</identifier>
        <datestamp>2014-07-02T22:19:39Z</datestamp>
        <setSpec>Brochures</setSpec>
      </header>
      <metadata>
        <oai_dc:dc xmlns:oai_dc="http://www.openarchives.org/OAI/2.0/oai_dc/" xmlns:dc="http://purl.org/dc/elements/1.1/" xmlns:xsi="http://www.w3.org/2001/XMLSchema-instance" xsi:schemaLocation="http://www.openarchives.org/OAI/2.0/oai_dc/ http://www.openarchives.org/OAI/2.0/oai_dc.xsd">
          <dc:title>Teachers resource sheets on oceanic species</dc:title>
          <dc:creator>Anon.</dc:creator>
          <dc:description>Anon. 2014. Teachers resource sheet on oceanic species. 2 p.</dc:description>
          <dc:date>2014</dc:date>
          <dc:type>Text</dc:type>
          <dc:format>application/pdf</dc:format>
          <dc:identifier>http://www.spc.int/DigitalLibrary/Doc/FAME/Brochures/Anon_14_07_oceanic_species.pdf</dc:identifier>
          <dc:language>en</dc:language>
          <dc:coverage>Cook Islands</dc:coverage>
        </oai_dc:dc>
      </metadata>
    </record>
    <record>
      <header>
        <identifier>oai:www.spc.int:a25b8a26-27cf-45da-a075-ffc70a511d81</identifier>
        <datestamp>2018-02-02T02:06:39Z</datestamp>
        <setSpec>WCPFC_SC12</setSpec>
      </header>
      <metadata>
        <oai_dc:dc xmlns:oai_dc="http://www.openarchives.org/OAI/2.0/oai_dc/" xmlns:dc="http://purl.org/dc/elements/1.1/" xmlns:xsi="http://www.w3.org/2001/XMLSchema-instance" xsi:schemaLocation="http://www.openarchives.org/OAI/2.0/oai_dc/ http://www.openarchives.org/OAI/2.0/oai_dc.xsd">
          <dc:title>Annual report to the commission - Part 1: information on fisheries, research, and statistics: Australia</dc:title>
          <dc:creator>Anon.</dc:creator>
          <dc:subject>Fisheries</dc:subject>
          <dc:subject>Tuna fisheries</dc:subject>
          <dc:description>Anon. 2016. Annual report to the commission - Part 1: information on fisheries, research, and statistics: Australia. [Bali, Indonesia]: Western and Central Pacific Fisheries Commission (WCPFC). Scientific Committee Regular Session, Bali, Indonesia, 3-11 August 2016, 12th</dc:description>
          <dc:date>2016</dc:date>
          <dc:type>Text</dc:type>
          <dc:format>application/pdf</dc:format>
          <dc:identifier>http://www.spc.int/DigitalLibrary/Doc/FAME/Meetings/WCPFC/SC12/AR_CCM_01_AUSTRALIA_PART_1.pdf</dc:identifier>
          <dc:language>en</dc:language>
          <dc:coverage>Australia</dc:coverage>
        </oai_dc:dc>
      </metadata>
    </record>
    <record>
      <header>
        <identifier>oai:www.spc.int:4680dd29-b95c-477a-8110-ffc79db50a4d</identifier>
        <datestamp>2012-07-30T21:28:24Z</datestamp>
        <setSpec>FFA</setSpec>
      </header>
      <metadata>
        <oai_dc:dc xmlns:oai_dc="http://www.openarchives.org/OAI/2.0/oai_dc/" xmlns:dc="http://purl.org/dc/elements/1.1/" xmlns:xsi="http://www.w3.org/2001/XMLSchema-instance" xsi:schemaLocation="http://www.openarchives.org/OAI/2.0/oai_dc/ http://www.openarchives.org/OAI/2.0/oai_dc.xsd">
          <dc:title>Maritime Boundaries Delimitation</dc:title>
          <dc:creator>Anon.</dc:creator>
          <dc:description>Anon. 1992. Maritime Boundaries Delimitation. Honiara, Solomon Islands: Forum Fisheries Agency. FFA Report 92/117. 9 p.</dc:description>
          <dc:publisher>Forum Fisheries Agency</dc:publisher>
          <dc:date>1992</dc:date>
          <dc:type>Text</dc:type>
          <dc:format>application/pdf</dc:format>
          <dc:identifier>http://www.spc.int/DigitalLibrary/Doc/FAME/FFA/Reports/FFA_1992_117.pdf</dc:identifier>
          <dc:language>en</dc:language>
        </oai_dc:dc>
      </metadata>
    </record>
    <record>
      <header>
        <identifier>oai:www.spc.int:ad96aebf-31f6-4d19-8066-ffd810410e92</identifier>
        <datestamp>2012-07-30T21:28:24Z</datestamp>
        <setSpec>All_Meetings</setSpec>
        <setSpec>FFA</setSpec>
        <setSpec>SPC_FFA_1995</setSpec>
      </header>
      <metadata>
        <oai_dc:dc xmlns:oai_dc="http://www.openarchives.org/OAI/2.0/oai_dc/" xmlns:dc="http://purl.org/dc/elements/1.1/" xmlns:xsi="http://www.w3.org/2001/XMLSchema-instance" xsi:schemaLocation="http://www.openarchives.org/OAI/2.0/oai_dc/ http://www.openarchives.org/OAI/2.0/oai_dc.xsd">
          <dc:title>Country Statement - Niue Island</dc:title>
          <dc:creator>Pasisi B.</dc:creator>
          <dc:subject>Fishery management</dc:subject>
          <dc:description>Pasisi B. 1995. Country Statement - Niue Island  [CP 9]. Noumea, New Caledonia: South Pacific Commission. South Pacific Commission and Forum Fisheries Agency Workshop on the Management of South Pacific Inshore Fisheries,  Noumea, New Caledonia, 1995. 4 p.</dc:description>
          <dc:publisher>South Pacific Commission</dc:publisher>
          <dc:date>1995</dc:date>
          <dc:type>Text</dc:type>
          <dc:format>application/pdf</dc:format>
          <dc:identifier>http://www.spc.int/DigitalLibrary/Doc/FAME/Meetings/SPC_FFA_Workshop_1995/CP9.pdf</dc:identifier>
          <dc:language>en</dc:language>
          <dc:coverage>Niue</dc:coverage>
        </oai_dc:dc>
      </metadata>
    </record>
    <record>
      <header>
        <identifier>oai:www.spc.int:351f8660-6509-40f3-b00a-ffe0a13be726</identifier>
        <datestamp>2015-09-29T04:05:43Z</datestamp>
        <setSpec>FishNews_VF_146</setSpec>
        <setSpec>All_FishNews</setSpec>
        <setSpec>All_InfoBull</setSpec>
      </header>
      <metadata>
        <oai_dc:dc xmlns:oai_dc="http://www.openarchives.org/OAI/2.0/oai_dc/" xmlns:dc="http://purl.org/dc/elements/1.1/" xmlns:xsi="http://www.w3.org/2001/XMLSchema-instance" xsi:schemaLocation="http://www.openarchives.org/OAI/2.0/oai_dc/ http://www.openarchives.org/OAI/2.0/oai_dc.xsd">
          <dc:title>Le corps humain comme instrument de mesure des animaux marins</dc:title>
          <dc:creator>Maclean J.</dc:creator>
          <dc:description>Maclean J. 2015. Le corps humain comme instrument de mesure des animaux marins. Lettre d'information sur les pêches de la CPS 146:22-23.</dc:description>
          <dc:date>2015</dc:date>
          <dc:type>Text</dc:type>
          <dc:format>application/pdf</dc:format>
          <dc:identifier>http://www.spc.int/DigitalLibrary/Doc/FAME/InfoBull/FishNews_VF/146/FishNews146_22_Maclean_VF.pdf</dc:identifier>
          <dc:language>fr</dc:language>
        </oai_dc:dc>
      </metadata>
    </record>
    <record>
      <header>
        <identifier>oai:www.spc.int:3f525fe7-f88d-44bd-bc45-fff05cc5ec78</identifier>
        <datestamp>2012-07-30T21:28:24Z</datestamp>
        <setSpec>All_Meetings</setSpec>
        <setSpec>NC_ALL</setSpec>
        <setSpec>RTMF_26</setSpec>
      </header>
      <metadata>
        <oai_dc:dc xmlns:oai_dc="http://www.openarchives.org/OAI/2.0/oai_dc/" xmlns:dc="http://purl.org/dc/elements/1.1/" xmlns:xsi="http://www.w3.org/2001/XMLSchema-instance" xsi:schemaLocation="http://www.openarchives.org/OAI/2.0/oai_dc/ http://www.openarchives.org/OAI/2.0/oai_dc.xsd">
          <dc:title>Exposé national Nouvelle-Calédonie</dc:title>
          <dc:creator>Anon.</dc:creator>
          <dc:subject>Fisheries</dc:subject>
          <dc:description>Anon. 1996. Exposé national Nouvelle-Calédonie  [Exposé national 2]. Nouméa, Nouvelle-Calédonie: Commission du Pacifique Sud. Conférence Technique Régionale sur les Pêches, Nouméa, Nouvelle-Calédonie, 5-9 août 1996, 26ème. 5 p.</dc:description>
          <dc:publisher>Commission du Pacifique Sud</dc:publisher>
          <dc:date>1996</dc:date>
          <dc:type>Text</dc:type>
          <dc:format>application/pdf</dc:format>
          <dc:identifier>http://www.spc.int/DigitalLibrary/Doc/FAME/Meetings/RTMF/26/CS2_VF.pdf</dc:identifier>
          <dc:language>fr</dc:language>
          <dc:coverage>New Caledonia</dc:coverage>
        </oai_dc:dc>
      </metadata>
    </record>
    <record>
      <header>
        <identifier>oai:www.spc.int:adee64c7-49b6-4674-bbce-fff12649a4f2</identifier>
        <datestamp>2015-08-20T04:51:58Z</datestamp>
        <setSpec>All_InfoBull</setSpec>
        <setSpec>All_FishNews</setSpec>
        <setSpec>FishNews_134</setSpec>
      </header>
      <metadata>
        <oai_dc:dc xmlns:oai_dc="http://www.openarchives.org/OAI/2.0/oai_dc/" xmlns:dc="http://purl.org/dc/elements/1.1/" xmlns:xsi="http://www.w3.org/2001/XMLSchema-instance" xsi:schemaLocation="http://www.openarchives.org/OAI/2.0/oai_dc/ http://www.openarchives.org/OAI/2.0/oai_dc.xsd">
          <dc:title>Proper fish handling for quality and safety</dc:title>
          <dc:creator>Beverly S.</dc:creator>
          <dc:description>Beverly S. 2011. Proper fish handling for quality and safety. SPC Fisheries Newsletter 134:29-33.</dc:description>
          <dc:date>2011</dc:date>
          <dc:type>Text</dc:type>
          <dc:format>application/pdf</dc:format>
          <dc:identifier>http://www.spc.int/DigitalLibrary/Doc/FAME/InfoBull/FishNews/134/FishNews134_29_Beverly.pdf</dc:identifier>
          <dc:language>en</dc:language>
        </oai_dc:dc>
      </metadata>
    </record>
    <record>
      <header>
        <identifier>oai:www.spc.int:5b22b28b-0efd-44d5-969d-fff191cef1c3</identifier>
        <datestamp>2017-11-01T23:50:42Z</datestamp>
        <setSpec>Brochures</setSpec>
      </header>
      <metadata>
        <oai_dc:dc xmlns:oai_dc="http://www.openarchives.org/OAI/2.0/oai_dc/" xmlns:dc="http://purl.org/dc/elements/1.1/" xmlns:xsi="http://www.w3.org/2001/XMLSchema-instance" xsi:schemaLocation="http://www.openarchives.org/OAI/2.0/oai_dc/ http://www.openarchives.org/OAI/2.0/oai_dc.xsd">
          <dc:title>Gaed long ol toksave blong ol fising komiuniti long Vanuatu - Fiseris manejmen 26: Si gras</dc:title>
          <dc:creator>Anon.</dc:creator>
          <dc:description>Anon. 2017. Gaed long ol toksave blong ol fising komiuniti long Vanuatu - Fiseris manejmen 26: Si gras.  Noumea, New Caledonia: Secretariat of the Pacific Community. 2 p.</dc:description>
          <dc:date>2017</dc:date>
          <dc:type>Text</dc:type>
          <dc:format>application/pdf</dc:format>
          <dc:identifier>http://www.spc.int/DigitalLibrary/Doc/FAME/Brochures/Anon_17_IS_26_Si_gras.pdf</dc:identifier>
          <dc:language>bi</dc:language>
          <dc:coverage>Vanuatu</dc:coverage>
        </oai_dc:dc>
      </metadata>
    </record>
    <record>
      <header>
        <identifier>oai:www.spc.int:0e9e764d-a63c-4344-b840-ffffdffc2fd4</identifier>
        <datestamp>2015-08-28T03:00:21Z</datestamp>
        <setSpec>LRF_VF_13</setSpec>
        <setSpec>All _LRF</setSpec>
        <setSpec>All_InfoBull</setSpec>
      </header>
      <metadata>
        <oai_dc:dc xmlns:oai_dc="http://www.openarchives.org/OAI/2.0/oai_dc/" xmlns:dc="http://purl.org/dc/elements/1.1/" xmlns:xsi="http://www.w3.org/2001/XMLSchema-instance" xsi:schemaLocation="http://www.openarchives.org/OAI/2.0/oai_dc/ http://www.openarchives.org/OAI/2.0/oai_dc.xsd">
          <dc:title>Ponte et élevage de larves de saumonées léopard à Gondol</dc:title>
          <dc:creator>Suwirya K.</dc:creator>
          <dc:description>Suwirya K. 2005. Ponte et élevage de larves de saumonées léopard à Gondol. Ressources marines et commercialisation, Bulletin d'information de la CPS 13:45.</dc:description>
          <dc:date>2005</dc:date>
          <dc:type>Text</dc:type>
          <dc:format>application/pdf</dc:format>
          <dc:identifier>http://www.spc.int/DigitalLibrary/Doc/FAME/InfoBull/LRF_VF/13/LRF13VF_45_Suwirya.pdf</dc:identifier>
          <dc:language>fr</dc:language>
          <dc:coverage>Indonesia</dc:coverage>
        </oai_dc:dc>
      </metadata>
    </record>
    <resumptionToken expirationDate="2018-09-21T11:16:07Z" completeListSize="11368" cursor="11300"></resumptionToken>
  </ListRecords>
</OAI-PMH>